Workbook

Sheet HES GRAL
C1: CANTIDAD | D1: UM | H1: CTRO COSTOS
C2: 1 | D2: C/U
A3: 3000000378 | B3: BRINCO 3.1.1 completo 6% | C3: 1 | D3: C/U | E3: =I3 -> 8602.1024 | F3: =ROUND(I3,3) -> 8602.102 | H3: LCBAJTA012 | I3: ='total gral.'!I49 -> 8602.1024 | J3: Brinco | K3: =I3-F3 -> 0.00035694556 | L3: =TRUNC(I3,3) -> 8602.102
A4: 3000000377 | B4: BRINCO 3.1.1 reducido 4,5% | C4: 1 | D4: C/U | E4: =I4 -> 1761113.3 | F4: =ROUND(I4,3) -> 1761113.3 | H4: LCBAJTA012 | I4: ='total gral.'!J49 -> 1761113.3 | K4: =I4-F4 -> 3.2291049e-05
A5: 3000000380 | B5: LA QUINIELA CONJUNTA 3.1.1 completo 6% | C5: 1 | D5: C/U | E5: =I5 -> 2920760.5 | F5: =ROUND(I5,3) -> 2920760.5 | H5: LCBAJPA007 | I5: ='total gral.'!I60 -> 2920760.5 | J5: Quiniela | K5: =I5-F5 -> 0.00046498561
A6: 3000000379 | B6: LA QUINIELA CONJUNTA 3.1.1 reducido 4,5% | C6: 1 | D6: C/U | E6: =I6 -> 5.9796896e+08 | F6: =ROUND(I6,3) -> 5.9796896e+08 | H6: LCBAJPA007 | I6: ='total gral.'!J60 -> 5.9796896e+08 | K6: =I6-F6 -> 0.00038123131
A7: 3000000382 | B7: LA QUINIELA POCEADA 3.1.1 completo 6% | C7: 1 | D7: C/U | E7: =I7 -> 206281.62 | F7: =ROUND(I7,3) -> 206281.62 | H7: LCBAJPA008 | I7: ='total gral.'!I61 -> 206281.62 | J7: Quiniela Poceada | K7: =I7-F7 -> 0.00042159826
A8: 3000000381 | B8: LA QUINIELA POCEADA 3.1.1 reducido 4,5% | C8: 1 | D8: C/U | E8: =I8 -> 42232153 | F8: =ROUND(I8,3) -> 42232153 | H8: LCBAJPA008 | I8: ='total gral.'!J61 -> 42232153 | K8: =I8-F8 -> -0.00031620264
A9: 3000000386 | B9: LA QUINIELA TOMBOLINA 3.1.1 completo 6% | C9: 1 | D9: C/U | E9: =I9 -> 3404.5934 | F9: =ROUND(I9,3) -> 3404.593 | H9: LCBAJPA009 | I9: ='total gral.'!I62 -> 3404.5934 | J9: Tombolina | K9: =I9-F9 -> 0.00040398956
A10: 3000000385 | B10: LA QUINIELA TOMBOLINA 3.1.1 reducido 4,5% | C10: 1 | D10: C/U | E10: =I10 -> 697024.35 | F10: =ROUND(I10,3) -> 697024.35 | H10: LCBAJPA009 | I10: ='total gral.'!J62 -> 697024.35 | K10: =I10-F10 -> 0.00014700799
A11: 3000000562 | B11: QUINIELA YA 3.1.1 completo 6% | C11: 1 | D11: C/U | E11: =I11 -> 6633.2063 | F11: =ROUND(I11,3) -> 6633.206 | H11: LCBAJPA011 | I11: ='total gral.'!I63 -> 6633.2063 | J11: Quiniela Ya | K11: =I11-F11 -> 0.00027592537
A12: 3000000563 | B12: QUINIELA YA 3.1.1 reducido 4,5% | C12: 1 | D12: C/U | E12: =I12 -> 1358020.1 | F12: =ROUND(I12,3) -> 1358020.1 | H12: LCBAJPA011 | I12: ='total gral.'!J63 -> 1358020.1 | K12: =I12-F12 -> -0.00028694398
A13: 3000000388 | B13: LOTO 5 3.1.1 completo 6% | C13: 1 | D13: C/U | E13: =I13 -> 5780.2217 | F13: =ROUND(I13,3) -> 5780.222 | H13: LCBAJPA006 | I13: ='total gral.'!I55 -> 5780.2217 | J13: Loto 5 Plus | K13: =I13-F13 -> -0.0002894186
A14: 3000000387 | B14: LOTO 5 3.1.1 reducido 4,5% | C14: 1 | D14: C/U | E14: =I14 -> 1183388.1 | F14: =ROUND(I14,3) -> 1183388.1 | H14: LCBAJPA006 | I14: ='total gral.'!J55 -> 1183388.1 | K14: =I14-F14 -> -0.00028293603
A15: 3000000392 | B15: LOTO DESQUITE 3.1.1 completo 6% | C15: 1 | D15: C/U | E15: =I15 -> 32250.347 | F15: =ROUND(I15,3) -> 32250.347 | H15: LCBAJPA003 | I15: ='total gral.'!I50 -> 32250.347 | J15: Loto Plus Desquite | K15: =I15-F15 -> 0.0002682883
A16: 3000000391 | B16: LOTO DESQUITE 3.1.1 reducido 4,5% | C16: 1 | D16: C/U | E16: =I16 -> 6602632 | F16: =ROUND(I16,3) -> 6602632 | H16: LCBAJPA003 | I16: ='total gral.'!J50 -> 6602632 | K16: =I16-F16 -> -0.0002012169
A17: 3000000396 | B17: LOTO SALE O SALE 3.1.1 completo 6% | C17: 1 | D17: C/U | E17: =I17 -> 16125.174 | F17: =ROUND(I17,3) -> 16125.174 | H17: LCBAJPA005 | I17: ='total gral.'!I51 -> 16125.174 | J17: Loto Plus SOS | K17: =I17-F17 -> -0.00036585585
A18: 3000000395 | B18: LOTO SALE O SALE 3.1.1 reducido 4,5% | C18: 1 | D18: C/U | E18: =I18 -> 3301316 | F18: =ROUND(I18,3) -> 3301316 | H18: LCBAJPA005 | I18: ='total gral.'!J51 -> 3301316 | K18: =I18-F18 -> 0.00039939117
A19: 3000000400 | B19: LOTO TRADICIONAL 3.1.1 completo6% | C19: 1 | D19: C/U | E19: =I19 -> 35475.382 | F19: =ROUND(I19,3) -> 35475.382 | H19: LCBAJPA004 | I19: ='total gral.'!I52 -> 35475.382 | J19: Loto Plus Tradicional | K19: =I19-F19 -> -4.8828661e-06
A20: 3000000399 | B20: LOTO TRADICIONAL 3.1.1 reducido 4,5% | C20: 1 | D20: C/U | E20: =I20 -> 7262895.2 | F20: =ROUND(I20,3) -> 7262895.2 | H20: LCBAJPA004 | I20: ='total gral.'!J52 -> 7262895.2 | K20: =I20-F20 -> -0.00032133795
A21: 3000000404 | B21: QUINI 6 REVANCHA 3.1.1 completo 6% | C21: 1 | D21: C/U | E21: =I21 -> 80581.127 | F21: =ROUND(I21,3) -> 80581.127 | H21: LCBAJTA004 | I21: ='total gral.'!I57 -> 80581.127 | J21: Quini6 Revancha | K21: =I21-F21 -> 0.00015754826
A22: 3000000403 | B22: QUINI 6 REVANCHA 3.1.1 reducido 4,5% | C22: 1 | D22: C/U | E22: =I22 -> 16497420 | F22: =ROUND(I22,3) -> 16497420 | H22: LCBAJTA004 | I22: ='total gral.'!J57 -> 16497420 | K22: =I22-F22 -> -0.00011815876
A23: 3000000406 | B23: QUINI 6 SIEMPRE SALE 3.1.1 completo 6% | C23: 1 | D23: C/U | E23: =I23 -> 80223.225 | F23: =ROUND(I23,3) -> 80223.225 | H23: LCBAJTA005 | I23: ='total gral.'!I58 -> 80223.225 | J23: Quini6 Siempre Sale | K23: =I23-F23 -> 0.00026632573
A24: 3000000405 | B24: QUINI 6 SIEMPRE SALE 3.1.1 reducido 4,5% | C24: 1 | D24: C/U | E24: =I24 -> 16424147 | F24: =ROUND(I24,3) -> 16424147 | H24: LCBAJTA005 | I24: ='total gral.'!J58 -> 16424147 | K24: =I24-F24 -> -0.00019974448
A25: 3000000408 | B25: QUINI 6 TRADICIONAL 3.1.1 completo 6% | C25: 1 | D25: C/U | E25: =I25 -> 161409.74 | F25: =ROUND(I25,3) -> 161409.74 | H25: LCBAJTA002 | I25: ='total gral.'!I59 -> 161409.74 | J25: QUINI 6 TRADICIONAL | K25: =I25-F25 -> 0.00017527613
A26: 3000000407 | B26: QUINI 6 TRADICIONAL 3.1.1 reducido 4,5% | C26: 1 | D26: C/U | E26: =I26 -> 33045508 | F26: =ROUND(I26,3) -> 33045508 | H26: LCBAJTA002 | I26: ='total gral.'!J59 -> 33045508 | K26: =I26-F26 -> 0.00036854297
A27: 3000000384 | B27: LA QUINIELA POCEADA 3.1.2 completo 3% | C27: 1 | D27: C/U | E27: =I27 -> 2551.2754 | F27: =ROUND(I27,3) -> 2551.275 | H27: LCBAJPA008 | I27: ='total gral.'!I79 -> 2551.2754 | K27: =I27-F27 -> 0.00039456324 | N27: =M27+L27 -> 0
A28: 3000000383 | B28: LA QUINIELA POCEADA 3.1.2 reducido 2,25% | C28: 1 | D28: C/U | E28: =I28 -> 522324.06 | F28: =ROUND(I28,3) -> 522324.07 | H28: LCBAJPA008 | I28: ='total gral.'!J79 -> 522324.06 | K28: =I28-F28 -> -4.592241e-05
A29: 3000000390 | B29: LOTO 5 3.1.2 completo 3% | C29: 1 | D29: C/U | E29: =I29 -> 9239.4944 | F29: =ROUND(I29,3) -> 9239.494 | H29: LCBAJPA006 | I29: ='total gral.'!I78 -> 9239.4944 | K29: =I29-F29 -> 0.00035172309
A30: 3000000389 | B30: LOTO 5 3.1.2 reducido 2,25% | C30: 1 | D30: C/U | E30: =I30 -> 1891606.9 | F30: =ROUND(I30,3) -> 1891606.9 | H30: LCBAJPA006 | I30: ='total gral.'!J78 -> 1891606.9 | K30: =I30-F30 -> 0.00023620808
A31: 3000000394 | B31: LOTO DESQUITE 3.1.2 completo 3% | C31: 1 | D31: C/U | E31: =I31 -> 104479.83 | F31: =ROUND(I31,3) -> 104479.83 | H31: LCBAJPA003 | I31: ='total gral.'!I73 -> 104479.83 | K31: =I31-F31 -> -7.4770389e-05
A32: 3000000393 | B32: LOTO DESQUITE 3.1.2 reducido 2,25% | C32: 1 | D32: C/U | E32: =I32 -> 21390216 | F32: =ROUND(I32,3) -> 21390216 | H32: LCBAJPA003 | I32: ='total gral.'!J73 -> 21390216 | K32: =I32-F32 -> 0.00018107891
A33: 3000000398 | B33: LOTO SALE O SALE 3.1.2 completo 3% | C33: 1 | D33: C/U | E33: =I33 -> 52239.917 | F33: =ROUND(I33,3) -> 52239.917 | H33: LCBAJPA005 | I33: ='total gral.'!I74 -> 52239.917 | K33: =I33-F33 -> -3.7385194e-05
A34: 3000000397 | B34: LOTO SALE O SALE 3.1.2 reducido 2,25% | C34: 1 | D34: C/U | E34: =I34 -> 10695108 | F34: =ROUND(I34,3) -> 10695108 | H34: LCBAJPA005 | I34: ='total gral.'!J74 -> 10695108 | K34: =I34-F34 -> 9.0539455e-05
A35: 3000000402 | B35: LOTO TRADICIONAL 3.1.2 completo 3% | C35: 1 | D35: C/U | E35: =I35 -> 114927.82 | F35: =ROUND(I35,3) -> 114927.82 | H35: LCBAJPA004 | I35: ='total gral.'!I75 -> 114927.82 | K35: =I35-F35 -> 0.00031775261
A36: 3000000401 | B36: LOTO TRADICIONAL 3.1.2 reducido 2,25% | C36: 1 | D36: C/U | E36: =I36 -> 23529238 | F36: =ROUND(I36,3) -> 23529238 | H36: LCBAJPA004 | I36: ='total gral.'!J75 -> 23529238 | K36: =I36-F36 -> 0.00019919127
A37: 3000000410 | B37: LA GRANDE DE LA NACIONAL 3.1.3 completo 3% | C37: 1 | D37: C/U | E37: =I37 -> 20621.875 | F37: =ROUND(I37,3)+0.005 -> 20621.88 | H37: LCBAJPA010 | I37: ='total gral.'!I81 -> 20621.875 | K37: =I37-F37 -> -0.0045127889
A38: 3000000409 | B38: 2,25%LA GRANDE DE LA NACIONAL 3.1.3 reducido | C38: 1 | D38: C/U | E38: =I38 -> 4221928.3 | F38: =ROUND(I38,3)+0.006 -> 4221928.3 | H38: LCBAJPA010 | I38: ='total gral.'!J81 -> 4221928.3 | K38: =I38-F38 -> -0.0055154078
A39: 3000000570 | B39: LOTO MATCH completo 3.1.1. completo 6% | C39: 1 | D39: C/U | E39: =I39 -> 35475.382 | F39: =ROUND(I39,3) -> 35475.382 | H39: LCBAJPA012 | I39: ='total gral.'!I53 -> 35475.382 | K39: =I39-F39 -> -4.8828661e-06
A40: 3000000571 | B40: LOTO MATCH reducido 3.1.1. reducifo 4,5% | C40: 1 | D40: C/U | E40: =I40 -> 7262895.2 | F40: =ROUND(I40,3) -> 7262895.2 | H40: LCBAJPA012 | I40: ='total gral.'!J53 -> 7262895.2 | K40: =I40-F40 -> -0.00032133795
A41: 3000000572 | B41: LOTO MULTIPLICADOR 3.1.1. completo 6% | C41: 1 | D41: C/U | E41: =I41 -> 41925.451 | F41: =ROUND(I41,3) -> 41925.451 | H41: LCBAJPA013 | I41: ='total gral.'!I54 -> 41925.451 | K41: =I41-F41 -> 0.00044877479
A42: 3000000573 | B42: LOTO MULTIPLICADOR 3.1.1. reducido 4,5% | C42: 1 | D42: C/U | E42: =I42 -> 8583421.6 | F42: =ROUND(I42,3) -> 8583421.6 | H42: LCBAJPA013 | I42: ='total gral.'!J54 -> 8583421.6 | K42: =I42-F42 -> 0.00043841824
A43: 3000000584 | B43: LOTO MATCH 3.1.2 completo 3% | C43: 1 | D43: C/U | E43: =I43 -> 114927.82 | F43: =ROUND(I43,3) -> 114927.82 | H43: LCBAJPA012 | I43: ='total gral.'!I76 -> 114927.82 | K43: =I43-F43 -> 0.00031775261
A44: 3000000585 | B44: LOTO MATCH 3.1.2 reducido 2,25% | C44: 1 | D44: C/U | E44: =I44 -> 23529238 | F44: =ROUND(I44,3) -> 23529238 | H44: LCBAJPA012 | I44: ='total gral.'!J76 -> 23529238 | K44: =I44-F44 -> 0.00019919127
A45: 3000000586 | B45: LOTO MULTIPLICADOR 3.1.2 completo 3% | C45: 1 | D45: C/U | E45: =I45 -> 135823.78 | F45: =ROUND(I45,3) -> 135823.78 | H45: LCBAJPA013 | I45: ='total gral.'!I77 -> 135823.78 | K45: =I45-F45 -> 0.00010279848
A46: 3000000587 | B46: LOTO MULTIPLICADOR 3.1.2 reducido 2,25% | C46: 1 | D46: C/U | E46: =I46 -> 27807281 | F46: =ROUND(I46,3) -> 27807281 | H46: LCBAJPA013 | I46: ='total gral.'!J77 -> 27807281 | K46: =I46-F46 -> 0.00023540482
B47: SUB TOTAL | E47: =SUM(E3:E46) -> 8.6195757e+08 | F47: =ROUND(I47,3) -> 0 | K47: =I47-F47 -> 0
F48: =ROUND(I48,3) -> 0 | K48: =I48-F48 -> 0
F49: =ROUND(I49,3) -> 0 | K49: =I49-F49 -> 0
A50: 3000000424 | B50: FACTURACION INTERNET -QUINIELA completo 14,65% | C50: 1 | D50: C/U | E50: =I50 -> 8867.172 | F50: =ROUND(I50,3) -> 8867.172 | H50: LCBAJOL007 | I50: ='total gral.'!I65 -> 8867.172 | K50: =I50-F50 -> 1.6735332e-05
A51: 3000000423 | B51: FACTURACION INTERNET -QUINIELA reducido 11% | C51: 1 | D51: C/U | E51: =I51 -> 2417757.7 | F51: =ROUND(I51,3) -> 2417757.7 | H51: LCBAJOL007 | I51: ='total gral.'!J65 -> 2417757.7 | K51: =I51-F51 -> 0.0004401016
A52: 3000000564 | B52: FACTURACION INTERNET -QUINIELA YA completo 14,65% | C52: 1 | D52: C/U | E52: =I52 -> 223.02601 | F52: =ROUND(I52,3) -> 223.026 | H52: LCBAJOL014 | I52: ='total gral.'!I66 -> 223.02601 | K52: =I52-F52 -> 1.4430921e-05
A53: 3000000565 | B53: FACTURACION INTERNET -QUINIELA YA reducido 11% | C53: 1 | D53: C/U | E53: =I53 -> 60811.142 | F53: =ROUND(I53,3) -> 60811.142 | H53: LCBAJOL014 | I53: ='total gral.'!J66 -> 60811.142 | K53: =I53-F53 -> -0.00020077816
A54: 3000000578 | B54: FACTURACION INTERNET -LOTO DESQUITE completo | C54: 1 | D54: C/U | E54: =I54 -> 950.66653 | F54: =ROUND(I54,3) -> 950.667 | H54: LCBAJOL011 | I54: ='total gral.'!I67 -> 950.66653 | K54: =I54-F54 -> -0.00047080563
A55: 3000000579 | B55: FACTURACION INTERNET -LOTO DESQUITE reducido | C55: 1 | D55: C/U | E55: =I55 -> 259212.44 | F55: =ROUND(I55,3) -> 259212.44 | H55: LCBAJOL011 | I55: ='total gral.'!J67 -> 259212.44 | K55: =I55-F55 -> -0.00022632026
A56: 3000000580 | B56: FACTURACION INTERNET -LOTO SOS completo | C56: 1 | D56: C/U | E56: =I56 -> 475.33326 | F56: =ROUND(I56,3) -> 475.333 | H56: LCBAJOL012 | I56: ='total gral.'!I68 -> 475.33326 | K56: =I56-F56 -> 0.00026459719
A57: 3000000581 | B57: FACTURACION INTERNET -LOTO SOS reducido | C57: 1 | D57: C/U | E57: =I57 -> 129606.22 | F57: =ROUND(I57,3) -> 129606.22 | H57: LCBAJOL012 | I57: ='total gral.'!J68 -> 129606.22 | K57: =I57-F57 -> 0.00038683988
A58: 3000000574 | B58: FACTURACION INTERNET -LOTO TRADICIONAL completo | C58: 1 | D58: C/U | E58: =I58 -> 1045.7332 | F58: =ROUND(I58,3) -> 1045.733 | H58: LCBAJOL009 | I58: ='total gral.'!I69 -> 1045.7332 | K58: =I58-F58 -> 0.00018211381
A59: 3000000575 | B59: FACTURACION INTERNET -LOTO TRADICIONAL reducido | C59: 1 | D59: C/U | E59: =I59 -> 285133.68 | F59: =ROUND(I59,3) -> 285133.68 | H59: LCBAJOL009 | I59: ='total gral.'!J69 -> 285133.68 | K59: =I59-F59 -> -0.00034895231
A60: 3000000576 | B60: FACTURACION INTERNET -LOTO MATCH completo | C60: 1 | D60: C/U | E60: =I60 -> 1045.7332 | F60: =ROUND(I60,3) -> 1045.733 | H60: LCBAJOL010 | I60: ='total gral.'!I70 -> 1045.7332 | K60: =I60-F60 -> 0.00018211381
A61: 3000000577 | B61: FACTURACION INTERNET -LOTO MATCH reducido | C61: 1 | D61: C/U | E61: =I61 -> 285133.68 | F61: =ROUND(I61,3) -> 285133.68 | H61: LCBAJOL010 | I61: ='total gral.'!J70 -> 285133.68 | K61: =I61-F61 -> -0.00034895231
A62: 3000000582 | B62: FACTURACION INTERNET -LOTO MULTIPLICADOR completo | C62: 1 | D62: C/U | E62: =I62 -> 1235.8665 | F62: =ROUND(I62,3) -> 1235.866 | H62: LCBAJOL013 | I62: ='total gral.'!I71 -> 1235.8665 | K62: =I62-F62 -> 0.00048795268
A63: 3000000583 | B63: FACTURACION INTERNET -LOTO MULTIPLICADOR reducido | C63: 1 | D63: C/U | E63: =I63 -> 336976.17 | F63: =ROUND(I63,3) -> 336976.17 | H63: LCBAJOL013 | I63: ='total gral.'!J71 -> 336976.17 | K63: =I63-F63 -> 0.00040578365
E64: =SUM(E50:E63) -> 3788474.5
F65: =SUM(F3:F46) -> 8.6195757e+08 | I65: =SUM(I3:I46) -> 8.6195757e+08
F66: =SUM(F50:F63) -> 3788474.5 | I66: =SUM(I50:I63) -> 3788474.5
A67: TOTAL | E67: =+E47+E64 -> 8.6574605e+08 | F67: =F66+F65 -> 8.6574605e+08 | I67: =I66+I65 -> 8.6574605e+08
A71: 3000000412 | B71: APUESTAS HIPICAS PALERMO completo | C71: =ROUND('total La plata y san isidro'!R23,2) -> 450530.97 | E71: =I71 -> 450530.97 | F71: LCBAJTA009 | I71: =+'total La plata y san isidro'!R23 -> 450530.97
A72: 3000000411 | B72: APUESTAS HIPICAS PALERMO reducido | C72: =ROUND('total La plata y san isidro'!R24,2)-0.01 -> 5512083.1 | D72: =C71+C72 -> 5962614 | E72: =I72 -> 5512083.1 | F72: LCBAJTA009 | H72: =SUM(F71:F72) -> 0 | I72: =+'total La plata y san isidro'!R24 -> 5512083.1
A73: 3000000414 | B73: APUESTAS HIPICAS SAN ISIDRO completo | C73: =ROUND('total La plata y san isidro'!R25,2) -> 578572.78 | E73: =I73 -> 578572.78 | F73: LCBAJTA011 | I73: =+'total La plata y san isidro'!R25 -> 578572.78
A74: 3000000413 | B74: APUESTAS HIPICAS SAN ISIDRO reducido | C74: =ROUND('total La plata y san isidro'!R26,2) -> 7078628.2 | E74: =I74 -> 7078628.2 | F74: LCBAJTA011 | I74: =+'total La plata y san isidro'!R26 -> 7078628.2
A75: 3000000416 | B75: APUESTAS HIPICAS LA PLATA completo | C75: =ROUND('total La plata y san isidro'!R27,2) -> 419266.26 | E75: =I75 -> 419266.26 | F75: LCBAJTA010 | I75: =+'total La plata y san isidro'!R27 -> 419266.26
A76: 3000000415 | B76: APUESTAS HIPICAS LA PLATA reducido | C76: =ROUND('total La plata y san isidro'!R28,2) -> 5129570.7 | D76: =C73+C74+C75+C76 -> 13206038 | E76: =I76 -> 5129570.7 | F76: LCBAJTA010 | H76: =SUM(F72:F76) -> 0 | I76: =+'total La plata y san isidro'!R28 -> 5129570.7
C77: =SUM(C71:C76) -> 19168652 | E77: =SUM(E71:E76) -> 19168652
B78: COPIAR Y PEGAR ESTO, OJO ES HES3
B79: =B71 -> APUESTAS HIPICAS PALERMO completo | C79: 1 | D79: C/U | F79: =C71 -> 450530.97 | H79: LCBAJTA009
B80: =B72 -> APUESTAS HIPICAS PALERMO reducido | C80: 1 | D80: C/U | F80: =C72 -> 5512083.1 | H80: LCBAJTA009
B81: =B73 -> APUESTAS HIPICAS SAN ISIDRO completo | C81: 1 | D81: C/U | F81: =C73 -> 578572.78 | H81: LCBAJTA011
B82: =B74 -> APUESTAS HIPICAS SAN ISIDRO reducido | C82: 1 | D82: C/U | F82: =C74 -> 7078628.2 | H82: LCBAJTA011
B83: =B75 -> APUESTAS HIPICAS LA PLATA completo | C83: 1 | D83: C/U | F83: =C75 -> 419266.26 | H83: LCBAJTA010
B84: =B76 -> APUESTAS HIPICAS LA PLATA reducido | C84: 1 | D84: C/U | F84: =C76 -> 5129570.7 | H84: LCBAJTA010
B88: CONSULTA IDENTIDAD RENAPER | C88: 1 | D88: C/U
B89: SERVICIO DE SMS | C89: 1 | D89: C/U | E89: 357039.5
B90: PASARELAS DE PAGO | C90: 1 | D90: C/U | E90: =342746.34+2128188.05 -> 2470934.4
B91: SERVICIOS EN LA NUBE | C91: 1 | D91: C/U
E92: =SUM(E89:E91) -> 2827973.9
A100: Hipicas | B100: 1000017723 | C100: =C77 -> 19168652
A101: Lotericos caba y pcias | B101: 1000017726 | C101: =F65 -> 8.6195757e+08
A102: WEB | B102: 1000017727 | C102: =F66 -> 3788474.5

Sheet mensual gral.
A1: JuegoCod | B1: juegoNom | C1: fecha | D1: sorteo | E1: onlineA | F1: onlineR | G1: cabaA | H1: cabaR | I1: totalA | J1: totalR
A2: 13 | B2: BRINCO | C2: 46026 | D2: 1335 | E2: 0 | F2: 0 | G2: 11606 | H2: 13927200 | I2: 11606 | J2: 13927200
A3: 13 | B3: BRINCO | C3: 46033 | D3: 1336 | E3: 0 | F3: 0 | G3: 11444 | H3: 13732800 | I3: 11444 | J3: 13732800
A4: 13 | B4: BRINCO | C4: 46040 | D4: 1337 | E4: 0 | F4: 0 | G4: 11236 | H4: 13483200 | I4: 11236 | J4: 13483200
A5: 13 | B5: BRINCO | C5: 46047 | D5: 1338 | E5: 0 | F5: 0 | G5: 11290 | H5: 13548000 | I5: 11290 | J5: 13548000
A6: 41 | B6: LA GRANDE DE LA CIUDAD | C6: 46018 | D6: 6018 | E6: 487 | F6: 3409000 | G6: 216153 | H6: 1513071000 | I6: 216640 | J6: 1516480000 | K6: =J6/7000 -> 216640
A7: 41 | B7: LA GRANDE DE LA CIUDAD | C7: 46039 | D7: 6019 | E7: 385 | F7: 1347500 | G7: 86337 | H7: 302179500 | I7: 86722 | J7: 303527000
A8: 5 | B8: LOTO 5 PLUS | C8: 46025 | D8: 1425 | E8: 103 | F8: 82400 | G8: 10375 | H8: 8300000 | I8: 45884 | J8: 36707200
A9: 5 | B9: LOTO 5 PLUS | C9: 46032 | D9: 1426 | E9: 148 | F9: 118400 | G9: 11567 | H9: 9253600 | I9: 48663 | J9: 38930400
A10: 5 | B10: LOTO 5 PLUS | C10: 46039 | D10: 1427 | E10: 253 | F10: 202400 | G10: 11184 | H10: 8947200 | I10: 46700 | J10: 37360000
A11: 5 | B11: LOTO 5 PLUS | C11: 46046 | D11: 1428 | E11: 166 | F11: 132800 | G11: 11515 | H11: 9212000 | I11: 47777 | J11: 38221600
A12: 5 | B12: LOTO 5 PLUS | C12: 46053 | D12: 1429 | E12: 170 | F12: 136000 | G12: 9644 | H12: 7715200 | I12: 42332 | J12: 33865600
A13: 7 | B13: LOTO SALE O SALE | C13: 46025 | D13: 3845 | E13: 472 | F13: 118000 | G13: 48959 | H13: 12239750 | I13: 391490 | J13: 97872500
A14: 7 | B14: LOTO SALE O SALE | C14: 46029 | D14: 3846 | E14: 434 | F14: 130200 | G14: 43204 | H14: 12961200 | I14: 310594 | J14: 93178200
A15: 7 | B15: LOTO SALE O SALE | C15: 46032 | D15: 3847 | E15: 408 | F15: 122400 | G15: 51135 | H15: 15340500 | I15: 390040 | J15: 117012000
A16: 7 | B16: LOTO SALE O SALE | C16: 46036 | D16: 3848 | E16: 447 | F16: 134100 | G16: 41956 | H16: 12586800 | I16: 303011 | J16: 90903300
A17: 7 | B17: LOTO SALE O SALE | C17: 46039 | D17: 3849 | E17: 405 | F17: 121500 | G17: 49307 | H17: 14792100 | I17: 379514 | J17: 113854200
A18: 7 | B18: LOTO SALE O SALE | C18: 46043 | D18: 3850 | E18: 457 | F18: 137100 | G18: 42223 | H18: 12666900 | I18: 303381 | J18: 91014300
... A219: 80 | B219: QUINIELA | C219: 46053 | D219: 51976 | E219: 275 | F219: 170650 | G219: 854791 | H219: 247205887 | I219: 855066 | J219: 247376537
A220: 82 | B220: QUINIELA POCEADA | C220: 46024 | D220: 9508 | E220: 80 | F220: 88000 | G220: 36547 | H220: 40201700 | I220: 37536 | J220: 41289600 | K220: =J220-H220-F220 -> 999900
A221: 82 | B221: QUINIELA POCEADA | C221: 46025 | D221: 9509 | E221: 91 | F221: 100100 | G221: 41256 | H221: 45381600 | I221: 42386 | J221: 46624600 | K221: =J221-H221-F221 -> 1142900
A222: 82 | B222: QUINIELA POCEADA | C222: 46027 | D222: 9510 | E222: 76 | F222: 83600 | G222: 37475 | H222: 41222500 | I222: 38416 | J222: 42257600 | K222: =J222-H222-F222 -> 951500
A223: 82 | B223: QUINIELA POCEADA | C223: 46028 | D223: 9511 | E223: 86 | F223: 94600 | G223: 38238 | H223: 42061800 | I223: 39237 | J223: 43160700 | K223: =J223-H223-F223 -> 1004300
A224: 82 | B224: QUINIELA POCEADA | C224: 46029 | D224: 9512 | E224: 76 | F224: 83600 | G224: 39697 | H224: 43666700 | I224: 40750 | J224: 44825000 | K224: =J224-H224-F224 -> 1074700
A225: 82 | B225: QUINIELA POCEADA | C225: 46030 | D225: 9513 | E225: 77 | F225: 84700 | G225: 38387 | H225: 42225700 | I225: 39451 | J225: 43396100 | K225: =J225-H225-F225 -> 1085700
A226: 82 | B226: QUINIELA POCEADA | C226: 46031 | D226: 9514 | E226: 94 | F226: 103400 | G226: 39815 | H226: 43796500 | I226: 40911 | J226: 45002100 | K226: =J226-H226-F226 -> 1102200
A227: 82 | B227: QUINIELA POCEADA | C227: 46032 | D227: 9515 | E227: 112 | F227: 123200 | G227: 43541 | H227: 47895100 | I227: 44797 | J227: 49276700 | K227: =J227-H227-F227 -> 1258400
A228: 82 | B228: QUINIELA POCEADA | C228: 46034 | D228: 9516 | E228: 92 | F228: 101200 | G228: 37487 | H228: 41235700 | I228: 38520 | J228: 42372000 | K228: =J228-H228-F228 -> 1035100
A229: 82 | B229: QUINIELA POCEADA | C229: 46035 | D229: 9517 | E229: 128 | F229: 140800 | G229: 39603 | H229: 43563300 | I229: 40752 | J229: 44827200 | K229: =J229-H229-F229 -> 1123100
A230: 82 | B230: QUINIELA POCEADA | C230: 46036 | D230: 9518 | E230: 85 | F230: 93500 | G230: 41273 | H230: 45400300 | I230: 42428 | J230: 46670800 | K230: =J230-H230-F230 -> 1177000
A231: 82 | B231: QUINIELA POCEADA | C231: 46037 | D231: 9519 | E231: 205 | F231: 225500 | G231: 37265 | H231: 40991500 | I231: 38478 | J231: 42325800 | K231: =J231-H231-F231 -> 1108800
... A245: 82 | B245: QUINIELA POCEADA | C245: 46053 | D245: 9533 | E245: 150 | F245: 165000 | G245: 49791 | H245: 54770100 | I245: 51061 | J245: 56167100 | K245: =J245-H245-F245 -> 1232000
A246: 79 | B246: QUINIELA YA | C246: 46024 | D246: 4173 | E246: 0 | F246: 0 | G246: 258 | H246: 88537 | I246: 258 | J246: 88537
A247: 79 | B247: QUINIELA YA | C247: 46024 | D247: 4174 | E247: 2 | F247: 600 | G247: 463 | H247: 134175 | I247: 465 | J247: 134775
A248: 79 | B248: QUINIELA YA | C248: 46024 | D248: 4175 | E248: 2 | F248: 200 | G248: 655 | H248: 218350 | I248: 657 | J248: 218550
A249: 79 | B249: QUINIELA YA | C249: 46024 | D249: 4176 | E249: 4 | F249: 1400 | G249: 610 | H249: 187940 | I249: 614 | J249: 189340
A250: 79 | B250: QUINIELA YA | C250: 46024 | D250: 4177 | E250: 0 | F250: 0 | G250: 804 | H250: 455545 | I250: 804 | J250: 455545
A251: 79 | B251: QUINIELA YA | C251: 46025 | D251: 4178 | E251: 8 | F251: 950 | G251: 199 | H251: 62340 | I251: 207 | J251: 63290
A252: 79 | B252: QUINIELA YA | C252: 46025 | D252: 4179 | E252: 0 | F252: 0 | G252: 207 | H252: 66250 | I252: 207 | J252: 66250
A253: 79 | B253: QUINIELA YA | C253: 46025 | D253: 4180 | E253: 1 | F253: 100 | G253: 894 | H253: 432360 | I253: 895 | J253: 432460
A254: 79 | B254: QUINIELA YA | C254: 46025 | D254: 4181 | E254: 4 | F254: 3105 | G254: 443 | H254: 130430 | I254: 447 | J254: 133535
A255: 79 | B255: QUINIELA YA | C255: 46025 | D255: 4182 | E255: 0 | F255: 0 | G255: 278 | H255: 88770 | I255: 278 | J255: 88770
A256: 79 | B256: QUINIELA YA | C256: 46027 | D256: 4183 | E256: 7 | F256: 1600 | G256: 182 | H256: 54895 | I256: 189 | J256: 56495 | L256: 49944 | M256: 50079 | N256: =M256-L256 -> 135
A257: 79 | B257: QUINIELA YA | C257: 46027 | D257: 4184 | E257: 13 | F257: 1300 | G257: 347 | H257: 198890 | I257: 360 | J257: 200190 | L257: 2271 | M257: 2350 | N257: =M257-L257 -> 79 | R257: 2271 | S257: 2405
A258: 79 | B258: QUINIELA YA | C258: 46027 | D258: 4185 | E258: 1 | F258: 100 | G258: 865 | H258: 452655 | I258: 866 | J258: 452755
A259: 79 | B259: QUINIELA YA | C259: 46027 | D259: 4186 | E259: 5 | F259: 500 | G259: 837 | H259: 629450 | I259: 842 | J259: 629950
A260: 79 | B260: QUINIELA YA | C260: 46027 | D260: 4187 | E260: 8 | F260: 2300 | G260: 1111 | H260: 868633 | I260: 1119 | J260: 870933
A261: 79 | B261: QUINIELA YA | C261: 46028 | D261: 4188 | E261: 4 | F261: 500 | G261: 336 | H261: 106025 | I261: 340 | J261: 106525
A262: 79 | B262: QUINIELA YA | C262: 46028 | D262: 4189 | E262: 1 | F262: 100 | G262: 522 | H262: 193085 | I262: 523 | J262: 193185
A263: 79 | B263: QUINIELA YA | C263: 46028 | D263: 4190 | E263: 3 | F263: 2100 | G263: 1341 | H263: 825607 | I263: 1344 | J263: 827707
A264: 79 | B264: QUINIELA YA | C264: 46028 | D264: 4191 | E264: 7 | F264: 850 | G264: 1412 | H264: 994626 | I264: 1419 | J264: 995476
A265: 79 | B265: QUINIELA YA | C265: 46028 | D265: 4192 | E265: 1 | F265: 100 | G265: 833 | H265: 468839 | I265: 834 | J265: 468939
A266: 79 | B266: QUINIELA YA | C266: 46029 | D266: 4193 | E266: 35 | F266: 3500 | G266: 575 | H266: 472200 | I266: 610 | J266: 475700
A267: 79 | B267: QUINIELA YA | C267: 46029 | D267: 4194 | E267: 1 | F267: 100 | G267: 534 | H267: 121215 | I267: 535 | J267: 121315
A268: 79 | B268: QUINIELA YA | C268: 46029 | D268: 4195 | E268: 47 | F268: 5300 | G268: 761 | H268: 181200 | I268: 808 | J268: 186500
A269: 79 | B269: QUINIELA YA | C269: 46029 | D269: 4196 | E269: 8 | F269: 900 | G269: 531 | H269: 176725 | I269: 539 | J269: 177625
... A401: 74 | B401: TOMBOLINA | C401: 46053 | D401: 4552 | E401: 35 | F401: 15250 | G401: 3633 | H401: 974155 | I401: 3668 | J401: 989405

Sheet palermo
A1: juego | B1: numero | D1: recaudacion cap | E1: recaudacion prov
A2: PALERMO | B2: 26001 | C2: 4012025 | D2: 51851230 | F2: 8 | G2: =IF(A2<>"",IF(IF(A2=A1,IF(B2<>B1,IF(B2-B1=1,"ok","MIRAR"),""),"CAMBIA JUEGO OK")="","mirar",IF(A2=A1,IF(B2<>B1,IF(B2-B1=1,"ok","MIRAR"),""),"CAMBIA JUEGO OK")),"") -> CAMBIA JUEGO OK
A3: PALERMO | B3: =B2+1 -> 26002 | C3: 6012025 | D3: 43098528 | F3: 8 | G3: =IF(A3<>"",IF(IF(A3=A2,IF(B3<>B2,IF(B3-B2=1,"ok","MIRAR"),""),"CAMBIA JUEGO OK")="","mirar",IF(A3=A2,IF(B3<>B2,IF(B3-B2=1,"ok","MIRAR"),""),"CAMBIA JUEGO OK")),"") -> ok
A4: PALERMO | B4: =B3+1 -> 26003 | C4: 10012025 | D4: 47244828 | F4: 8 | G4: =IF(A4<>"",IF(IF(A4=A3,IF(B4<>B3,IF(B4-B3=1,"ok","MIRAR"),""),"CAMBIA JUEGO OK")="","mirar",IF(A4=A3,IF(B4<>B3,IF(B4-B3=1,"ok","MIRAR"),""),"CAMBIA JUEGO OK")),"") -> ok | I4: PARA CARGAR: "1) MIRAR BALANCE Y CARGAR: VENTA NETA MATERIAL DE JUEGO" 2) MIRAR LOS ARCHIVOS tjd y hacer la cuenta +venta-cancelacion-devolucion
A5: PALERMO | B5: =B4+1 -> 26004 | C5: 12012025 | D5: 40411746 | F5: 8 | G5: =IF(A5<>"",IF(IF(A5=A4,IF(B5<>B4,IF(B5-B4=1,"ok","MIRAR"),""),"CAMBIA JUEGO OK")="","mirar",IF(A5=A4,IF(B5<>B4,IF(B5-B4=1,"ok","MIRAR"),""),"CAMBIA JUEGO OK")),"") -> ok
A6: PALERMO | B6: =B5+1 -> 26005 | C6: 13012025 | D6: 38166467 | F6: 8 | G6: =IF(A6<>"",IF(IF(A6=A5,IF(B6<>B5,IF(B6-B5=1,"ok","MIRAR"),""),"CAMBIA JUEGO OK")="","mirar",IF(A6=A5,IF(B6<>B5,IF(B6-B5=1,"ok","MIRAR"),""),"CAMBIA JUEGO OK")),"") -> ok
A7: PALERMO | B7: =B6+1 -> 26006 | C7: 18012025 | D7: 18403615 | F7: 8 | G7: =IF(A7<>"",IF(IF(A7=A6,IF(B7<>B6,IF(B7-B6=1,"ok","MIRAR"),""),"CAMBIA JUEGO OK")="","mirar",IF(A7=A6,IF(B7<>B6,IF(B7-B6=1,"ok","MIRAR"),""),"CAMBIA JUEGO OK")),"") -> ok
A8: PALERMO | B8: =B7+1 -> 26007 | C8: 20012025 | D8: 40232597 | F8: 8 | G8: =IF(A8<>"",IF(IF(A8=A7,IF(B8<>B7,IF(B8-B7=1,"ok","MIRAR"),""),"CAMBIA JUEGO OK")="","mirar",IF(A8=A7,IF(B8<>B7,IF(B8-B7=1,"ok","MIRAR"),""),"CAMBIA JUEGO OK")),"") -> ok
A9: PALERMO | B9: =B8+1 -> 26008 | C9: 24012025 | D9: 42284418 | F9: 8 | G9: =IF(A9<>"",IF(IF(A9=A8,IF(B9<>B8,IF(B9-B8=1,"ok","MIRAR"),""),"CAMBIA JUEGO OK")="","mirar",IF(A9=A8,IF(B9<>B8,IF(B9-B8=1,"ok","MIRAR"),""),"CAMBIA JUEGO OK")),"") -> ok
A10: PALERMO | B10: =B9+1 -> 26009 | C10: 27012025 | D10: 34823882 | F10: 8 | G10: =IF(A10<>"",IF(IF(A10=A9,IF(B10<>B9,IF(B10-B9=1,"ok","MIRAR"),""),"CAMBIA JUEGO OK")="","mirar",IF(A10=A9,IF(B10<>B9,IF(B10-B9=1,"ok","MIRAR"),""),"CAMBIA JUEGO OK")),"") -> ok
A11: PALERMO | B11: =B10+1 -> 26010 | C11: 31012025 | D11: 47383716 | F11: 8 | G11: =IF(A11<>"",IF(IF(A11=A10,IF(B11<>B10,IF(B11-B10=1,"ok","MIRAR"),""),"CAMBIA JUEGO OK")="","mirar",IF(A11=A10,IF(B11<>B10,IF(B11-B10=1,"ok","MIRAR"),""),"CAMBIA JUEGO OK")),"") -> ok
G12: =IF(A12<>"",IF(IF(A12=A11,IF(B12<>B11,IF(B12-B11=1,"ok","MIRAR"),""),"CAMBIA JUEGO OK")="","mirar",IF(A12=A11,IF(B12<>B11,IF(B12-B11=1,"ok","MIRAR"),""),"CAMBIA JUEGO OK")),"")
D13: =SUM(D2:D12) -> 403901027 | G13: =IF(A13<>"",IF(IF(A13=A12,IF(B13<>B12,IF(B13-B12=1,"ok","MIRAR"),""),"CAMBIA JUEGO OK")="","mirar",IF(A13=A12,IF(B13<>B12,IF(B13-B12=1,"ok","MIRAR"),""),"CAMBIA JUEGO OK")),"")
G14: =IF(A14<>"",IF(IF(A14=A13,IF(B14<>B13,IF(B14-B13=1,"ok","MIRAR"),""),"CAMBIA JUEGO OK")="","mirar",IF(A14=A13,IF(B14<>B13,IF(B14-B13=1,"ok","MIRAR"),""),"CAMBIA JUEGO OK")),"")
G15: =IF(A15<>"",IF(IF(A15=A14,IF(B15<>B14,IF(B15-B14=1,"ok","MIRAR"),""),"CAMBIA JUEGO OK")="","mirar",IF(A15=A14,IF(B15<>B14,IF(B15-B14=1,"ok","MIRAR"),""),"CAMBIA JUEGO OK")),"")
G16: =IF(A16<>"",IF(IF(A16=A15,IF(B16<>B15,IF(B16-B15=1,"ok","MIRAR"),""),"CAMBIA JUEGO OK")="","mirar",IF(A16=A15,IF(B16<>B15,IF(B16-B15=1,"ok","MIRAR"),""),"CAMBIA JUEGO OK")),"")
G17: =IF(A17<>"",IF(IF(A17=A16,IF(B17<>B16,IF(B17-B16=1,"ok","MIRAR"),""),"CAMBIA JUEGO OK")="","mirar",IF(A17=A16,IF(B17<>B16,IF(B17-B16=1,"ok","MIRAR"),""),"CAMBIA JUEGO OK")),"")
G18: =IF(A18<>"",IF(IF(A18=A17,IF(B18<>B17,IF(B18-B17=1,"ok","MIRAR"),""),"CAMBIA JUEGO OK")="","mirar",IF(A18=A17,IF(B18<>B17,IF(B18-B17=1,"ok","MIRAR"),""),"CAMBIA JUEGO OK")),"")
G19: =IF(A19<>"",IF(IF(A19=A18,IF(B19<>B18,IF(B19-B18=1,"ok","MIRAR"),""),"CAMBIA JUEGO OK")="","mirar",IF(A19=A18,IF(B19<>B18,IF(B19-B18=1,"ok","MIRAR"),""),"CAMBIA JUEGO OK")),"")
G20: =IF(A20=A19,IF(B20<>B19,IF(B20-B19=1,"ok","MIRAR"),""),"CAMBIA JUEGO OK")
G21: =IF(A21=A20,IF(B21<>B20,IF(B21-B20=1,"ok","MIRAR"),""),"CAMBIA JUEGO OK")
G22: =IF(A22=A21,IF(B22<>B21,IF(B22-B21=1,"ok","MIRAR"),""),"CAMBIA JUEGO OK")
G23: =IF(A23=A22,IF(B23<>B22,IF(B23-B22=1,"ok","MIRAR"),""),"CAMBIA JUEGO OK")
G24: =IF(A24=A23,IF(B24<>B23,IF(B24-B23=1,"ok","MIRAR"),""),"CAMBIA JUEGO OK")
G25: =IF(A25=A24,IF(B25<>B24,IF(B25-B24=1,"ok","MIRAR"),""),"CAMBIA JUEGO OK")
G26: =IF(A26=A25,IF(B26<>B25,IF(B26-B25=1,"ok","MIRAR"),""),"CAMBIA JUEGO OK")
G27: =IF(A27=A26,IF(B27<>B26,IF(B27-B26=1,"ok","MIRAR"),""),"CAMBIA JUEGO OK")
G28: =IF(A28=A27,IF(B28<>B27,IF(B28-B27=1,"ok","MIRAR"),""),"CAMBIA JUEGO OK")
G29: =IF(A29=A28,IF(B29<>B28,IF(B29-B28=1,"ok","MIRAR"),""),"CAMBIA JUEGO OK")
G30: =IF(A30=A29,IF(B30<>B29,IF(B30-B29=1,"ok","MIRAR"),""),"CAMBIA JUEGO OK")
G31: =IF(A31=A30,IF(B31<>B30,IF(B31-B30=1,"ok","MIRAR"),""),"CAMBIA JUEGO OK")
... G460: =IF(A460=A459,IF(B460<>B459,IF(B460-B459=1,"ok","MIRAR"),""),"CAMBIA JUEGO OK")

Sheet la plata y san isidro
A1: juego | B1: numero | D1: recaudacion cap | E1: recaudacion prov | I1: PARA CARGAR: "1) MIRAR BALANCE Y CARGAR: VENTA NETA MATERIAL DE JUEGO" 2) MIRAR LOS ARCHIVOS tjd y hacer la cuenta +venta-cancelacion-devolucion
A2: LA PLATA | B2: 26001 | C2: 2012025 | D2: 42261617 | F2: 8 | G2: =IF(A2=A1,IF(B2<>B1,IF(B2-B1=1,"ok","MIRAR"),""),"CAMBIA JUEGO OK") -> CAMBIA JUEGO OK
A3: LA PLATA | B3: =B2+1 -> 26002 | C3: 7012025 | D3: 41695120 | F3: 8 | G3: =IF(A3=A2,IF(B3<>B2,IF(B3-B2=1,"ok","MIRAR"),""),"CAMBIA JUEGO OK") -> ok
A4: LA PLATA | B4: =B3+1 -> 26003 | C4: 9012025 | D4: 17301028 | F4: 8 | G4: =IF(A4=A3,IF(B4<>B3,IF(B4-B3=1,"ok","MIRAR"),""),"CAMBIA JUEGO OK") -> ok
A5: LA PLATA | B5: =B4+1 -> 26004 | C5: 14012025 | D5: 36560707 | F5: 8 | G5: =IF(A5=A4,IF(B5<>B4,IF(B5-B4=1,"ok","MIRAR"),""),"CAMBIA JUEGO OK") -> ok
A6: LA PLATA | B6: =B5+1 -> 26005 | C6: 16012025 | D6: 35306809 | F6: 8 | G6: =IF(A6=A5,IF(B6<>B5,IF(B6-B5=1,"ok","MIRAR"),""),"CAMBIA JUEGO OK") -> ok
A7: LA PLATA | B7: =B6+1 -> 26006 | C7: 19012025 | D7: 40807354 | F7: 8 | G7: =IF(A7=A6,IF(B7<>B6,IF(B7-B6=1,"ok","MIRAR"),""),"CAMBIA JUEGO OK") -> ok
A8: LA PLATA | B8: =B7+1 -> 26007 | C8: 21012025 | D8: 37187547 | F8: 8 | G8: =IF(A8=A7,IF(B8<>B7,IF(B8-B7=1,"ok","MIRAR"),""),"CAMBIA JUEGO OK") -> ok
A9: LA PLATA | B9: =B8+1 -> 26008 | C9: 25012025 | D9: 36269969 | F9: 8 | G9: =IF(A9=A8,IF(B9<>B8,IF(B9-B8=1,"ok","MIRAR"),""),"CAMBIA JUEGO OK") -> ok
A10: LA PLATA | B10: =B9+1 -> 26009 | C10: 28012025 | D10: 43994222 | F10: 8 | G10: =IF(A10=A9,IF(B10<>B9,IF(B10-B9=1,"ok","MIRAR"),""),"CAMBIA JUEGO OK") -> ok
A11: LA PLATA | B11: =B10+1 -> 26010 | C11: 28012026 | D11: 44487841 | F11: 8 | G11: =IF(A11=A10,IF(B11<>B10,IF(B11-B10=1,"ok","MIRAR"),""),"CAMBIA JUEGO OK") -> ok
D12: =SUM(D2:D11) -> 375872214 | F12: 8 | G12: =IF(A12=A11,IF(B12<>B11,IF(B12-B11=1,"ok","MIRAR"),""),"CAMBIA JUEGO OK") -> CAMBIA JUEGO OK
A13: SAN ISIDRO | B13: 26001 | C13: 3012025 | D13: 55168759 | F13: 8 | G13: =IF(A13=A11,IF(B13<>B11,IF(B13-B11=1,"ok","MIRAR"),""),"CAMBIA JUEGO OK") -> CAMBIA JUEGO OK
A14: SAN ISIDRO | B14: =B13+1 -> 26002 | C14: 5012025 | D14: 28830728 | F14: 8 | G14: =IF(A14=A13,IF(B14<>B13,IF(B14-B13=1,"ok","MIRAR"),""),"CAMBIA JUEGO OK") -> ok
A15: SAN ISIDRO | B15: =B14+1 -> 26003 | C15: 8012025 | D15: 60227636 | F15: 8 | G15: =IF(A15=A14,IF(B15<>B14,IF(B15-B14=1,"ok","MIRAR"),""),"CAMBIA JUEGO OK") -> ok
A16: SAN ISIDRO | B16: =B15+1 -> 26004 | C16: 11012025 | D16: 76164817 | F16: 8 | G16: =IF(A16=A15,IF(B16<>B15,IF(B16-B15=1,"ok","MIRAR"),""),"CAMBIA JUEGO OK") -> ok
A17: SAN ISIDRO | B17: =B16+1 -> 26005 | C17: 15012025 | D17: 52006091 | F17: 8 | G17: =IF(A17=A16,IF(B17<>B16,IF(B17-B16=1,"ok","MIRAR"),""),"CAMBIA JUEGO OK") -> ok
A18: SAN ISIDRO | B18: =B17+1 -> 26006 | C18: 17012025 | D18: 67379574 | F18: 8 | G18: =IF(A18=A17,IF(B18<>B17,IF(B18-B17=1,"ok","MIRAR"),""),"CAMBIA JUEGO OK") -> ok
A19: SAN ISIDRO | B19: =B18+1 -> 26007 | C19: 22012025 | D19: 52762221 | F19: 8 | G19: =IF(A19=A18,IF(B19<>B18,IF(B19-B18=1,"ok","MIRAR"),""),"CAMBIA JUEGO OK") -> ok
A20: SAN ISIDRO | B20: =B19+1 -> 26008 | C20: 23012025 | D20: 55229165 | F20: 8 | G20: =IF(A20=A19,IF(B20<>B19,IF(B20-B19=1,"ok","MIRAR"),""),"CAMBIA JUEGO OK") -> ok
A21: SAN ISIDRO | B21: =B20+1 -> 26009 | C21: 26012025 | D21: 25220728 | F21: 8 | G21: =IF(A21=A20,IF(B21<>B20,IF(B21-B20=1,"ok","MIRAR"),""),"CAMBIA JUEGO OK") -> ok
A22: SAN ISIDRO | B22: =B21+1 -> 26010 | C22: 26012026 | D22: 45700796 | F22: 8 | G22: =IF(A22=A21,IF(B22<>B21,IF(B22-B21=1,"ok","MIRAR"),""),"CAMBIA JUEGO OK") -> ok
D23: =SUM(D13:D22) -> 518690515 | F23: 8 | G23: =IF(A23=A22,IF(B23<>B22,IF(B23-B22=1,"ok","MIRAR"),""),"CAMBIA JUEGO OK") -> CAMBIA JUEGO OK
G24: =IF(A24=A23,IF(B24<>B23,IF(B24-B23=1,"ok","MIRAR"),""),"CAMBIA JUEGO OK")
G25: =IF(A25=A24,IF(B25<>B24,IF(B25-B24=1,"ok","MIRAR"),""),"CAMBIA JUEGO OK")
G26: =IF(A26=A25,IF(B26<>B25,IF(B26-B25=1,"ok","MIRAR"),""),"CAMBIA JUEGO OK")
G27: =IF(A27=A26,IF(B27<>B26,IF(B27-B26=1,"ok","MIRAR"),""),"CAMBIA JUEGO OK")
G28: =IF(A28=A27,IF(B28<>B27,IF(B28-B27=1,"ok","MIRAR"),""),"CAMBIA JUEGO OK")
G29: =IF(A29=A28,IF(B29<>B28,IF(B29-B28=1,"ok","MIRAR"),""),"CAMBIA JUEGO OK")
G30: =IF(A30=A29,IF(B30<>B29,IF(B30-B29=1,"ok","MIRAR"),""),"CAMBIA JUEGO OK")
G31: =IF(A31=A30,IF(B31<>B30,IF(B31-B30=1,"ok","MIRAR"),""),"CAMBIA JUEGO OK")

Sheet total gral.
E1: Capital Federal | G1: Provincias
A2: RECAUDACIÓN POR JUEGO / INSTANCIA | E2: Recaudación | F2: Participación | G2: Recaudación | H2: Participación
A3: Borratina Tradicional | E3: =SUMIF($A$10:$A$86,A3,$E$10:$E$86) -> 0 | F3: =E3/$E$18 -> 0 | J3: 105000000
A4: BRINCO | D4: =E4/($E$18+$G$18)*100 -> 0.18289473 | E4: =SUM(SUMIF('mensual gral.'!$B:$B,'total gral.'!A4,'mensual gral.'!$J:$J)-SUMIF('mensual gral.'!$B:$B,'total gral.'!A4,'mensual gral.'!$F:$F))*0.9 -> 49222080 | F4: =E4/$E$18 -> 0.0023665124 | I4: =E4/$E$35 -> 0.001711044 | J4: =$J$3*I4 -> 179659.61 | K4: =6-(6*20.2/100) -> 4.788 | L4: =J4*K$4/100 -> 8602.1024 | N4: =E4-J4 -> 49042420 | O4: =K4*0.75 -> 3.591 | P4: =N4*$O$4/100 -> 1761113.3
A5: LOTO DESQUITE | D5: =E5/($E$18+$G$18)*100 -> 0.685695 | E5: =(SUMIF('mensual gral.'!$B:$B,'total gral.'!A5,'mensual gral.'!$H:$H))*0.75 -> 184539675 | F5: =E5/$E$18 -> 0.0088723481 | G5: =SUM(SUMIF('mensual gral.'!$B:$B,'total gral.'!A5,'mensual gral.'!$J:$J)-SUMIF('mensual gral.'!$B:$B,'total gral.'!A5,'mensual gral.'!$H:$H)-SUMIF('mensual gral.'!$B:$B,'total gral.'!A5,'mensual gral.'!$F:$F))*0.75 -> 1195687875 | H5: =G5/$G$18 -> 0.19558555 | I5: =E5/$E$35 -> 0.0064149157 | J5: =$J$3*I5 -> 673566.15 | L5: =J5*K$4/100 -> 32250.347 | N5: =E5-J5 -> 1.8386611e+08 | P5: =N5*$O$4/100 -> 6602632
A6: LOTO SALE O SALE | D6: =E6/($E$18+$G$18)*100 -> 0.3428475 | E6: =(SUMIF('mensual gral.'!$B:$B,'total gral.'!A6,'mensual gral.'!$H:$H))*0.75 -> 92269838 | F6: =E6/$E$18 -> 0.0044361741 | G6: =SUM(SUMIF('mensual gral.'!$B:$B,'total gral.'!A6,'mensual gral.'!$J:$J)-SUMIF('mensual gral.'!$B:$B,'total gral.'!A6,'mensual gral.'!$H:$H)-SUMIF('mensual gral.'!$B:$B,'total gral.'!A6,'mensual gral.'!$F:$F))*0.75 -> 5.9784394e+08 | H6: =G6/$G$18 -> 0.097792776 | I6: =E6/$E$35 -> 0.0032074579 | J6: =$J$3*I6 -> 336783.08 | L6: =J6*K$4/100 -> 16125.174 | N6: =E6-J6 -> 91933054 | P6: =N6*$O$4/100 -> 3301316
A7: LOTO PLUS TRADICIONAL | D7: =E7/($E$18+$G$18)*100 -> 0.75426449 | E7: =(SUMIF('mensual gral.'!$B:$B,'total gral.'!A7,'mensual gral.'!$H:$H))*0.75 -> 2.0299364e+08 | F7: =E7/$E$18 -> 0.0097595829 | G7: =SUM(SUMIF('mensual gral.'!$B:$B,'total gral.'!A7,'mensual gral.'!$J:$J)-SUMIF('mensual gral.'!$B:$B,'total gral.'!A7,'mensual gral.'!$H:$H)-SUMIF('mensual gral.'!$B:$B,'total gral.'!A7,'mensual gral.'!$F:$F))*0.75 -> 1.3152567e+09 | H7: =G7/$G$18 -> 0.21514411 | I7: =E7/$E$35 -> 0.0070564073 | J7: =$J$3*I7 -> 740922.77 | L7: =J7*K$4/100 -> 35475.382 | N7: =E7-J7 -> 2.0225272e+08 | P7: =N7*$O$4/100 -> 7262895.2
A8: LOTO 5 PLUS | D8: =E8/($E$18+$G$18)*100 -> 0.12289694 | E8: =SUM(SUMIF('mensual gral.'!$B:$B,'total gral.'!A8,'mensual gral.'!$H:$H)+SUMIF('mensual gral.'!$B:$B,'total gral.'!A8,'mensual gral.'!$F:$F))*0.75 -> 33075000 | F8: =E8/$E$18 -> 0.0015901887 | G8: =SUM(SUMIF('mensual gral.'!$B:$B,'total gral.'!A8,'mensual gral.'!$J:$J)-SUMIF('mensual gral.'!$B:$B,'total gral.'!A8,'mensual gral.'!$H:$H)-SUMIF('mensual gral.'!$B:$B,'total gral.'!A8,'mensual gral.'!$F:$F))*0.75 -> 105738600 | H8: =G8/$G$18 -> 0.017296272 | I8: =E8/$E$35 -> 0.0011497437 | J8: =$J$3*I8 -> 120723.09 | L8: =J8*K$4/100 -> 5780.2217 | N8: =E8-J8 -> 32954277 | P8: =N8*$O$4/100 -> 1183388.1
A9: LOTO MATCH | D9: =E9/($E$18+$G$18)*100 -> 0.75426449 | E9: =(SUMIF('mensual gral.'!$B:$B,'total gral.'!A9,'mensual gral.'!$H:$H))*0.75 -> 2.0299364e+08 | F9: =E9/$E$18 -> 0.0097595829 | G9: =SUM(SUMIF('mensual gral.'!$B:$B,'total gral.'!A9,'mensual gral.'!$J:$J)-SUMIF('mensual gral.'!$B:$B,'total gral.'!A9,'mensual gral.'!$H:$H)-SUMIF('mensual gral.'!$B:$B,'total gral.'!A9,'mensual gral.'!$F:$F))*0.75 -> 1.3152567e+09 | H9: =G9/$G$18 -> 0.21514411 | I9: =E9/$E$35 -> 0.0070564073 | J9: =$J$3*I9 -> 740922.77 | L9: =J9*K$4/100 -> 35475.382 | N9: =E9-J9 -> 2.0225272e+08 | P9: =N9*$O$4/100 -> 7262895.2
A10: LOTO NUMERO PLUS | D10: =E10/($E$18+$G$18)*100 -> 0.89140349 | E10: =(SUMIF('mensual gral.'!$B:$B,'total gral.'!A10,'mensual gral.'!$H:$H))*0.75 -> 2.3990158e+08 | F10: =E10/$E$18 -> 0.011534053 | G10: =SUM(SUMIF('mensual gral.'!$B:$B,'total gral.'!A10,'mensual gral.'!$J:$J)-SUMIF('mensual gral.'!$B:$B,'total gral.'!A10,'mensual gral.'!$H:$H)-SUMIF('mensual gral.'!$B:$B,'total gral.'!A10,'mensual gral.'!$F:$F))*0.75 -> 1.5543942e+09 | H10: =G10/$G$18 -> 0.25426122 | I10: =E10/$E$35 -> 0.0083393904 | J10: =$J$3*I10 -> 875636 | L10: =J10*K$4/100 -> 41925.451 | N10: =E10-J10 -> 2.3902594e+08 | P10: =N10*$O$4/100 -> 8583421.6
A11: QUINI 6 REVANCHA | D11: =E11/($E$18+$G$18)*100 -> 1.7132862 | E11: =SUM(SUMIF('mensual gral.'!$B:$B,'total gral.'!A11,'mensual gral.'!$J:$J)-SUMIF('mensual gral.'!$B:$B,'total gral.'!A11,'mensual gral.'!$F:$F))*0.9 -> 461093175 | F11: =E11/$E$18 -> 0.022168562 | G11: =SUM(SUMIF('mensual gral.'!$B:$B,'total gral.'!A11,'mensual gral.'!$J:$J)-SUMIF('mensual gral.'!$B:$B,'total gral.'!A11,'mensual gral.'!$H:$H))-SUMIF('mensual gral.'!$B:$B,'total gral.'!A11,'mensual gral.'!$F:$F) -> 0 | H11: =G11/$G$18 -> 0 | I11: =E11/$E$35 -> 0.01602839 | J11: =$J$3*I11 -> 1682980.9 | L11: =J11*K$4/100 -> 80581.127 | N11: =E11-J11 -> 4.5941019e+08 | P11: =N11*$O$4/100 -> 16497420
A12: QUINI 6 SIEMPRE SALE | D12: =E12/($E$18+$G$18)*100 -> 1.7056766 | E12: =SUM(SUMIF('mensual gral.'!$B:$B,'total gral.'!A12,'mensual gral.'!$J:$J)-SUMIF('mensual gral.'!$B:$B,'total gral.'!A12,'mensual gral.'!$F:$F))*0.9 -> 459045225 | F12: =E12/$E$18 -> 0.0220701 | G12: =SUM(SUMIF('mensual gral.'!$B:$B,'total gral.'!A12,'mensual gral.'!$J:$J)-SUMIF('mensual gral.'!$B:$B,'total gral.'!A12,'mensual gral.'!$H:$H))-SUMIF('mensual gral.'!$B:$B,'total gral.'!A12,'mensual gral.'!$F:$F) -> 0 | H12: =G12/$G$18 -> 0 | I12: =E12/$E$35 -> 0.0159572 | J12: =$J$3*I12 -> 1675506 | L12: =J12*K$4/100 -> 80223.225 | N12: =E12-J12 -> 4.5736972e+08 | P12: =N12*$O$4/100 -> 16424147
A13: QUINI 6 | D13: =E13/($E$18+$G$18)*100 -> 3.4318344 | E13: =SUM((SUMIF('mensual gral.'!$B:$B,'total gral.'!A13,'mensual gral.'!$J:$J)-SUMIF('mensual gral.'!$B:$B,'total gral.'!A13,'mensual gral.'!$F:$F))*0.9)*2 -> 923602500 | F13: =E13/$E$18 -> 0.044405209 | G13: =SUM(SUMIF('mensual gral.'!$B:$B,'total gral.'!A13,'mensual gral.'!$J:$J)-SUMIF('mensual gral.'!$B:$B,'total gral.'!A13,'mensual gral.'!$H:$H))-SUMIF('mensual gral.'!$B:$B,'total gral.'!A13,'mensual gral.'!$F:$F) -> 0 | H13: =G13/$G$18 -> 0 | I13: =E13/$E$35 -> 0.032106008 | J13: =$J$3*I13 -> 3371130.8 | L13: =J13*K$4/100 -> 161409.74 | N13: =E13-J13 -> 9.2023137e+08 | P13: =N13*$O$4/100 -> 33045508
A14: QUINIELA | D14: =E14/($E$18+$G$18)*100 -> 62.100133 | E14: =SUM(SUMIF('mensual gral.'!$B:$B,'total gral.'!A14,'mensual gral.'!$J:$J)-SUMIF('mensual gral.'!$B:$B,'total gral.'!A14,'mensual gral.'!$F:$F)) -> 16712880328 | F14: =E14/$E$18 -> 0.80352635 | G14: =SUM(SUMIF('mensual gral.'!$B:$B,'total gral.'!A14,'mensual gral.'!$J:$J)-SUMIF('mensual gral.'!$B:$B,'total gral.'!A14,'mensual gral.'!$H:$H))-SUMIF('mensual gral.'!$B:$B,'total gral.'!A14,'mensual gral.'!$F:$F) -> 0 | H14: =G14/$G$18 -> 0 | I14: =E14/$E$35 -> 0.58096839 | J14: =$J$3*I14 -> 61001681 | L14: =J14*K$4/100 -> 2920760.5 | N14: =E14-J14 -> 1.6651879e+10 | P14: =N14*$O$4/100 -> 5.9796896e+08
A15: QUINIELA POCEADA | D15: =E15/($E$18+$G$18)*100 -> 4.3858837 | E15: =SUM(SUMIF('mensual gral.'!$B:$B,'total gral.'!A15,'mensual gral.'!$H:$H)+SUMIF('mensual gral.'!$B:$B,'total gral.'!A15,'mensual gral.'!$F:$F)) -> 1180363800 | F15: =E15/$E$18 -> 0.056749848 | G15: =SUM(SUMIF('mensual gral.'!$B:$B,'total gral.'!A15,'mensual gral.'!$J:$J)-SUMIF('mensual gral.'!$B:$B,'total gral.'!A15,'mensual gral.'!$H:$H))-SUMIF('mensual gral.'!$B:$B,'total gral.'!A15,'mensual gral.'!$F:$F) -> 29197300 | H15: =G15/$G$18 -> 0.0047759705 | I15: =E15/$E$35 -> 0.041031471 | J15: =$J$3*I15 -> 4308304.4 | L15: =J15*K$4/100 -> 206281.62 | N15: =E15-J15 -> 1.1760555e+09 | P15: =N15*$O$4/100 -> 42232153
A16: TOMBOLINA | D16: =E16/($E$18+$G$18)*100 -> 0.07238721 | E16: =SUM(SUMIF('mensual gral.'!$B:$B,'total gral.'!A16,'mensual gral.'!$H:$H)+SUMIF('mensual gral.'!$B:$B,'total gral.'!A16,'mensual gral.'!$F:$F)) -> 19481420 | F16: =E16/$E$18 -> 0.00093663295 | G16: =SUM(SUMIF('mensual gral.'!$B:$B,'total gral.'!A16,'mensual gral.'!$J:$J)-SUMIF('mensual gral.'!$B:$B,'total gral.'!A16,'mensual gral.'!$H:$H))-SUMIF('mensual gral.'!$B:$B,'total gral.'!A16,'mensual gral.'!$F:$F) -> 0 | H16: =G16/$G$18 -> 0 | I16: =E16/$E$35 -> 0.00067720758 | J16: =$J$3*I16 -> 71106.796 | L16: =J16*K$4/100 -> 3404.5934 | N16: =E16-J16 -> 19410313 | P16: =N16*$O$4/100 -> 697024.35
A17: QUINIELA YA | D17: =E17/($E$18+$G$18)*100 -> 0.14103279 | E17: =SUM(SUMIF('mensual gral.'!$B:$B,'total gral.'!A17,'mensual gral.'!$J:$J)-SUMIF('mensual gral.'!$B:$B,'total gral.'!A17,'mensual gral.'!$F:$F)) -> 37955862 | F17: =E17/$E$18 -> 0.0018248521 | H17: =G17/$G$18 -> 0 | I17: =E17/$E$35 -> 0.0013194109 | J17: =$J$3*I17 -> 138538.14 | L17: =J17*K$4/100 -> 6633.2063
E18: =SUM(E3:E17) -> 20799417765 | F18: =SUM(F3:F17) -> 1 | G18: =SUM(G3:G17) -> 6113375275 | H18: =SUM(H3:H17) -> 1
A21: QUINIELA | E21: =SUM(SUMIF('mensual gral.'!$B:$B,'total gral.'!A21,'mensual gral.'!$F:$F)) -> 22085231 | F21: =+E21/E28 -> 0.64052822
A22: QUINIELA YA | E22: =SUM(SUMIF('mensual gral.'!$B:$B,'total gral.'!A22,'mensual gral.'!$F:$F)) -> 555485 | F22: =+E22/E28 -> 0.016110487
A23: LOTO DESQUITE | E23: =SUM(SUMIF('mensual gral.'!$B:$B,'total gral.'!A23,'mensual gral.'!$F:$F)) -> 2367800 | F23: =+E23/E28 -> 0.068672259
A24: LOTO SALE O SALE | E24: =SUM(SUMIF('mensual gral.'!$B:$B,'total gral.'!A24,'mensual gral.'!$F:$F)) -> 1183900 | F24: =+E24/E28 -> 0.03433613
A25: LOTO PLUS TRADICIONAL | E25: =SUM(SUMIF('mensual gral.'!$B:$B,'total gral.'!A25,'mensual gral.'!$F:$F)) -> 2604580 | F25: =+E25/E28 -> 0.075539485
A26: LOTO MATCH | E26: =SUM(SUMIF('mensual gral.'!$B:$B,'total gral.'!A26,'mensual gral.'!$F:$F)) -> 2604580 | F26: =+E26/E28 -> 0.075539485
A27: LOTO NUMERO PLUS | E27: =SUM(SUMIF('mensual gral.'!$B:$B,'total gral.'!A27,'mensual gral.'!$F:$F)) -> 3078140 | F27: =+E27/E28 -> 0.089273937
E28: =SUM(E21:E27) -> 34479716 | J28: LA GRANDE DE LA CIUDAD
J29: Lotería Tradicional
A30: SUMATORIA RECAUDACION | E30: Recaudación | F30: Participación | G30: Porcentaje Ofertado | H30: Porcentaje con Reducción | J30: Valor a facturar = Fabricado * Fracción Ordinaria | K30: Recaudación Dentro del tope | L30: Recaudación Sobre el Tope | N30: 216640 | O30: 750
A31: FACTURACION ON LINE - CAPITAL FEDERAL | E31: =E18 -> 20799417765 | F31: =E31/E35 -> 0.72302345 | G31: =6%/1.21 -> 0.049586777 | H31: =G31-(G31*$D$40) -> 0.037190083 | N31: 86722 | O31: 1500
A32: FACTURACION INTERNET - CAPITAL FEDERAL | E32: =E28 -> 34479716 | F32: =E32/E35 -> 0.0011985741 | G32: =11%/1.21 -> 0.090909091 | H32: =(0.1465-(0.1465*D40))/1.21 -> 0.090805785
A33: FACTURACION CONSOLIDACIÓN PROVINCIAS | E33: =G18 -> 6113375275 | F33: =E33/E35 -> 0.21251141 | G33: =3%/1.21 -> 0.024793388 | H33: =G33-(G33*$D$40) -> 0.018595041 | M33: vendidos | N33: valor ordinario | O33: valor venta
A34: FACTURACIÓN BILLETES | E34: =SUM(SUMIF('mensual gral.'!$B:$B,J28,'mensual gral.'!$H:$H)+SUMIF('mensual gral.'!$B:$B,'total gral.'!J28,'mensual gral.'!$F:$F)) -> 1820007000 | F34: =+E34/E35 -> 0.063266566 | G34: 0.0242 | H34: =G34-(G34*$D$40) -> 0.01815 | J34: =(M34*N34)+(M35*N35) -> 292563000 | K34: =IFERROR((E81/E34)*J34,0) -> 171654.92 | L34: =IFERROR((F86/E34)*J34,0) -> 0 | M34: 216640 | N34: 750 | O34: 1500
A35: TOTALES | E35: =SUM(E31:E34) -> 28767279756 | F35: =E35/E35 -> 1 | M35: 86722 | N35: 1500
G37: =+G31*1.21 -> 0.06 | H37: =+H31*1.21 -> 0.045
E38: =+E35 -> 28767279756 | G38: =+G33*1.21 -> 0.03 | H38: =+H33*1.21 -> 0.0225
A39: TOPE ESTIPULADO | E39: 105000000
A40: EXCEDENTE - PORCENTAJE SOBRE TOPE | D40: 0.25 | E40: =+E35-E39 -> 28662279756
A41: LÍMITE DE REDUCCIÓN DE PORCENTAJE
B42: ON LINE | C42: 3.1.1 | D42: =6%/1.21*(1-0.25) -> 0.037190083 | H42: =14.65*0.25 -> 3.6625
B43: CONSOLIDACIÓN | C43: 3.1.2 | D43: =3%/1.21*(1-0.25) -> 0.018595041 | H43: =14.62-H42 -> 10.9575
B44: LT | C44: 3.1.3 | D44: =3%*(1-0.25) -> 0.0225
B45: web | C45: 3.1.1bis | D45: =14.65*0.25/100 -> 0.036625
A46: FACTURACIÓN | E46: Recaudación | I46: Facturación UTE
E47: Dentro del tope | F47: Sobre el tope | G47: Total | H47: Control | I47: Importe sobre Recaudación dentro del Tope | J47: Importe sobre Recaduación Sobre el Tope | K47: Total
A48: FACTURACION ON LINE - CAPITAL FEDERAL
B49: Brinco | D49: 3.1.1 COMPLETO AL 6% | E49: =$E$39*$F$31*F4 -> 179659.61 | F49: =$E$40*$F$31*F4 -> 49042420 | G49: =SUM(E49:F49) -> 49222080 | H49: =IF(E4=G49,"OK","ERROR") -> OK | I49: =(E49*$G$31)*0.798*1.21 -> 8602.1024 | J49: =(F49*$H$31)*0.798*1.21 -> 1761113.3 | K49: =I49+J49 -> 1769715.4
B50: Loto Plus Desquite | D50: 3.1.1 COMPLETO AL 6% | E50: =$E$39*$F$31*F5 -> 673566.15 | F50: =$E$40*$F$31*F5 -> 1.8386611e+08 | G50: =SUM(E50:F50) -> 184539675 | H50: =IF(E5=G50,"OK","ERROR") -> OK | I50: =(E50*$G$31)*0.798*1.21 -> 32250.347 | J50: =(F50*$H$31)*0.798*1.21 -> 6602632 | K50: =I50+J50 -> 6634882.3
B51: Loto Plus SOS | D51: 3.1.1 COMPLETO AL 6% | E51: =$E$39*$F$31*F6 -> 336783.08 | F51: =$E$40*$F$31*F6 -> 91933054 | G51: =SUM(E51:F51) -> 92269838 | H51: =IF(E6=G51,"OK","ERROR") -> OK | I51: =(E51*$G$31)*0.798*1.21 -> 16125.174 | J51: =(F51*$H$31)*0.798*1.21 -> 3301316 | K51: =I51+J51 -> 3317441.2
B52: Loto Plus Tradicional | D52: 3.1.1 COMPLETO AL 6% | E52: =$E$39*$F$31*F7 -> 740922.77 | F52: =$E$40*$F$31*F7 -> 2.0225272e+08 | G52: =SUM(E52:F52) -> 2.0299364e+08 | H52: =IF(E7=G52,"OK","ERROR") -> OK | I52: =(E52*$G$31)*0.798*1.21 -> 35475.382 | J52: =(F52*$H$31)*0.798*1.21 -> 7262895.2 | K52: =I52+J52 -> 7298370.5
B53: LOTO MATCH | D53: 3.1.1 COMPLETO AL 6% | E53: =$E$39*$F$31*F9 -> 740922.77 | F53: =$E$40*$F$31*F9 -> 2.0225272e+08 | G53: =SUM(E53:F53) -> 2.0299364e+08 | H53: =IF(E9=G53,"OK","ERROR") -> OK | I53: =(E53*$G$31)*0.798*1.21 -> 35475.382 | J53: =(F53*$H$31)*0.798*1.21 -> 7262895.2 | K53: =I53+J53 -> 7298370.5
B54: LOTO NUMERO PLUS | D54: 3.1.1 COMPLETO AL 6% | E54: =$E$39*$F$31*F10 -> 875636 | F54: =$E$40*$F$31*F10 -> 2.3902594e+08 | G54: =SUM(E54:F54) -> 2.3990158e+08 | H54: =IF(E10=G54,"OK","ERROR") -> OK | I54: =(E54*$G$31)*0.798*1.21 -> 41925.451 | J54: =(F54*$H$31)*0.798*1.21 -> 8583421.6 | K54: =I54+J54 -> 8625347
B55: Loto 5 Plus | D55: 3.1.1 COMPLETO AL 6% | E55: =$E$39*$F$31*F8 -> 120723.09 | F55: =$E$40*$F$31*F8 -> 32954277 | G55: =SUM(E55:F55) -> 33075000 | H55: =IF(E8=G55,"OK","ERROR") -> OK | I55: =(E55*$G$31)*0.798*1.21 -> 5780.2217 | J55: =(F55*$H$31)*0.798*1.21 -> 1183388.1 | K55: =I55+J55 -> 1189168.3
B57: Quini6 Revancha | D57: 3.1.1 COMPLETO AL 6% | E57: =$E$39*$F$31*F11 -> 1682980.9 | F57: =$E$40*$F$31*F11 -> 4.5941019e+08 | G57: =SUM(E57:F57) -> 4.6109318e+08 | H57: =IF(E11=G57,"OK","ERROR") -> OK | I57: =(E57*$G$31)*0.798*1.21 -> 80581.127 | J57: =(F57*$H$31)*0.798*1.21 -> 16497420 | K57: =I57+J57 -> 16578001
B58: Quini6 Siempre Sale | D58: 3.1.1 COMPLETO AL 6% | E58: =$E$39*$F$31*F12 -> 1675506 | F58: =$E$40*$F$31*F12 -> 4.5736972e+08 | G58: =SUM(E58:F58) -> 459045225 | H58: =IF(E12=G58,"OK","ERROR") -> OK | I58: =(E58*$G$31)*0.798*1.21 -> 80223.225 | J58: =(F58*$H$31)*0.798*1.21 -> 16424147 | K58: =I58+J58 -> 16504370
B59: Quini6 Tradicional | D59: 3.1.1 COMPLETO AL 6% | E59: =$E$39*$F$31*F13 -> 3371130.8 | F59: =$E$40*$F$31*F13 -> 9.2023137e+08 | G59: =SUM(E59:F59) -> 923602500 | H59: =IF(E13=G59,"OK","ERROR") -> OK | I59: =(E59*$G$31)*0.798*1.21 -> 161409.74 | J59: =(F59*$H$31)*0.798*1.21 -> 33045508 | K59: =I59+J59 -> 33206918
B60: Quiniela | D60: 3.1.1 COMPLETO AL 6% | E60: =$E$39*$F$31*F14 -> 61001681 | F60: =$E$40*$F$31*F14 -> 1.6651879e+10 | G60: =SUM(E60:F60) -> 1.671288e+10 | H60: =IF(E14=G60,"OK","ERROR") -> OK | I60: =(E60*$G$31)*0.798*1.21 -> 2920760.5 | J60: =(F60*$H$31)*0.798*1.21 -> 5.9796896e+08 | K60: =I60+J60 -> 6.0088972e+08
B61: Quiniela Poceada | D61: 3.1.1 COMPLETO AL 6% | E61: =$E$39*$F$31*F15 -> 4308304.4 | F61: =$E$40*$F$31*F15 -> 1.1760555e+09 | G61: =SUM(E61:F61) -> 1180363800 | H61: =IF(E15=G61,"OK","ERROR") -> OK | I61: =(E61*$G$31)*0.798*1.21 -> 206281.62 | J61: =(F61*$H$31)*0.798*1.21 -> 42232153 | K61: =I61+J61 -> 42438434
B62: Tombolina | D62: 3.1.1 COMPLETO AL 6% | E62: =$E$39*$F$31*F16 -> 71106.796 | F62: =$E$40*$F$31*F16 -> 19410313 | G62: =SUM(E62:F62) -> 19481420 | H62: =IF(E16=G62,"OK","ERROR") -> OK | I62: =(E62*$G$31)*0.798*1.21 -> 3404.5934 | J62: =(F62*$H$31)*0.798*1.21 -> 697024.35 | K62: =I62+J62 -> 700428.94
B63: Quiniela Ya | D63: 3.1.1 COMPLETO AL 6% | E63: =$E$39*$F$31*F17 -> 138538.14 | F63: =$E$40*$F$31*F17 -> 37817324 | G63: =SUM(E63:F63) -> 37955862 | I63: =(E63*$G$31)*0.798*1.21 -> 6633.2063 | J63: =(F63*$H$31)*0.798*1.21 -> 1358020.1 | K63: =I63+J63 -> 1364653.3 | L63: =SUM(K49:K63) -> 7.4781582e+08
A64: WEB
B65: Quiniela web | D65: 3.1.1.Bis COMPLETO AL 11% | E65: =E39*$F$32*F21 -> 80610.655 | F65: =E21-E65 -> 22004620 | G65: =SUM(E65:F65) -> 22085231 | I65: =(E65*$G$32)*1.21 -> 8867.172 | J65: =(F65*$H$32)*1.21 -> 2417757.7 | K65: =I65+J65 -> 2426624.8
B66: Quiniela Ya web | D66: 3.1.1.Bis COMPLETO AL 11% | E66: =E39*$F$32*F22 -> 2027.5092 | F66: =E22-E66 -> 553457.49 | G66: =SUM(E66:F66) -> 555485 | I66: =(E66*$G$32)*1.21 -> 223.02601 | J66: =(F66*$H$32)*1.21 -> 60811.142 | K66: =I66+J66 -> 61034.168
B67: Loto Plus Desquite web | D67: 3.1.1.Bis COMPLETO AL 11% | E67: =E39*$F$32*F23 -> 8642.423 | F67: =E23-E67 -> 2359157.6 | G67: =SUM(E67:F67) -> 2367800 | I67: =(E67*$G$32)*1.21 -> 950.66653 | J67: =(F67*$H$32)*1.21 -> 259212.44 | K67: =I67+J67 -> 260163.11
B68: Loto Plus SOS web | D68: 3.1.1.Bis COMPLETO AL 11% | E68: =E39*$F$32*F24 -> 4321.2115 | F68: =E24-E68 -> 1179578.8 | G68: =SUM(E68:F68) -> 1183900 | I68: =(E68*$G$32)*1.21 -> 475.33326 | J68: =(F68*$H$32)*1.21 -> 129606.22 | K68: =I68+J68 -> 130081.55
B69: Loto Plus Tradicional web | D69: 3.1.1.Bis COMPLETO AL 11% | E69: =E39*$F$32*F25 -> 9506.6653 | F69: =E25-E69 -> 2595073.3 | G69: =SUM(E69:F69) -> 2604580 | I69: =(E69*$G$32)*1.21 -> 1045.7332 | J69: =(F69*$H$32)*1.21 -> 285133.68 | K69: =I69+J69 -> 286179.42
B70: LOTO MATCH web | D70: 3.1.1.Bis COMPLETO AL 11% | E70: =E39*$F$32*F26 -> 9506.6653 | F70: =E26-E70 -> 2595073.3 | G70: =SUM(E70:F70) -> 2604580 | I70: =(E70*$G$32)*1.21 -> 1045.7332 | J70: =(F70*$H$32)*1.21 -> 285133.68 | K70: =I70+J70 -> 286179.42
B71: LOTO NUMERO PLUS web | D71: 3.1.1.Bis COMPLETO AL 11% | E71: =E39*$F$32*F27 -> 11235.15 | F71: =E27-E71 -> 3066904.9 | G71: =SUM(E71:F71) -> 3078140 | I71: =(E71*$G$32)*1.21 -> 1235.8665 | J71: =(F71*$H$32)*1.21 -> 336976.17 | K71: =I71+J71 -> 338212.04 | L71: =SUM(K65:K71) -> 3788474.5
A72: FACTURACION CONSOLIDACIÓN PROVINCIAS
B73: Loto Plus Desquite | D73: 3.1.1 COMPLETO AL 3% | E73: =$E$39*$F$33*H5 -> 4364237 | F73: =+$E$40*$F$33*H5 -> 1.1913236e+09 | G73: =SUM(E73:F73) -> 1195687875 | H73: =IF(G5=G73,"OK","ERROR") -> OK | I73: =(E73*$G$33)*0.798*1.21 -> 104479.83 | J73: =(F73*$H$33)*0.798*1.21 -> 21390216 | K73: =I73+J73 -> 21494696
B74: Loto Plus SOS | D74: 3.1.1 COMPLETO AL 3% | E74: =$E$39*$F$33*H6 -> 2182118.5 | F74: =+$E$40*$F$33*H6 -> 5.9566182e+08 | G74: =SUM(E74:F74) -> 5.9784394e+08 | H74: =IF(G6=G74,"OK","ERROR") -> OK | I74: =(E74*$G$33)*0.798*1.21 -> 52239.917 | J74: =(F74*$H$33)*0.798*1.21 -> 10695108 | K74: =I74+J74 -> 10747348
B75: Loto Plus Tradicional | D75: 3.1.1 COMPLETO AL 3% | E75: =$E$39*$F$33*H7 -> 4800660.7 | F75: =+$E$40*$F$33*H7 -> 1.310456e+09 | G75: =SUM(E75:F75) -> 1.3152567e+09 | H75: =IF(G7=G75,"OK","ERROR") -> OK | I75: =(E75*$G$33)*0.798*1.21 -> 114927.82 | J75: =(F75*$H$33)*0.798*1.21 -> 23529238 | K75: =I75+J75 -> 23644165
B76: LOTO MATCH | D76: 3.1.1 COMPLETO AL 3% | E76: =$E$39*$F$33*H9 -> 4800660.7 | F76: =+$E$40*$F$33*H9 -> 1.310456e+09 | G76: =SUM(E76:F76) -> 1.3152567e+09 | I76: =(E76*$G$33)*0.798*1.21 -> 114927.82 | J76: =(F76*$H$33)*0.798*1.21 -> 23529238 | K76: =I76+J76 -> 23644165
B77: LOTO NUMERO PLUS | D77: 3.1.1 COMPLETO AL 3% | E77: =$E$39*$F$33*H10 -> 5673508.1 | F77: =+$E$40*$F$33*H10 -> 1.5487207e+09 | G77: =SUM(E77:F77) -> 1.5543942e+09 | I77: =(E77*$G$33)*0.798*1.21 -> 135823.78 | J77: =(F77*$H$33)*0.798*1.21 -> 27807281 | K77: =I77+J77 -> 27943104
B78: Loto 5 Plus | D78: 3.1.1 COMPLETO AL 3% | E78: =$E$39*$F$33*H8 -> 385943.79 | F78: =+$E$40*$F$33*H8 -> 1.0535266e+08 | G78: =SUM(E78:F78) -> 1.057386e+08 | H78: =IF(G8=G78,"OK","ERROR") -> OK | I78: =(E78*$G$33)*0.798*1.21 -> 9239.4944 | J78: =(F78*$H$33)*0.798*1.21 -> 1891606.9 | K78: =I78+J78 -> 1900846.4
B79: Quiniela Poceada | D79: 3.1.1 COMPLETO AL 3% | E79: =E39*$F$33*H15 -> 106569.57 | F79: =+$E$40*$F$33*H15 -> 29090730 | G79: =SUM(E79:F79) -> 29197300 | H79: =IF(G15=G79,"OK","ERROR") -> OK | I79: =(E79*$G$33)*0.798*1.21 -> 2551.2754 | J79: =(F79*$H$33)*0.798*1.21 -> 522324.06 | K79: =I79+J79 -> 524875.34
B80: la grande para calcular no tocar | E80: =+E39*F34 -> 6642989.4 | F80: =+E40*F34 -> 1.813364e+09 | G80: =SUM(E80:F80) -> 1.820007e+09
B81: la grande | E81: =IFERROR(E80/G80*J34,0) -> 1067849.1 | F81: =IF(E81=0,0,J34-E81) -> 2.9149515e+08 | I81: =(E81*$G$34)*0.798 -> 20621.875 | J81: =(F81*$H$34)*0.798 -> 4221928.3 | K81: =I81+J81 -> 4242550.2 | L81: =SUM(K73:K81) -> 1.1414175e+08
A82: FACTURACIÓN RECAUDACION EXCEDENTE AL TOPE | E82: =SUM(E48:E81)-E80 -> 99424860 | F82: =SUM(F48:F81)-F80 -> 2.7140411e+10 | G82: =SUM(G48:G81) -> 28767279756 | I82: =SUM(I49:I81) -> 4203583.4 | J82: =SUM(J49:J81) -> 8.6154247e+08 | K82: =I82+J82 -> 8.6574605e+08
G88: =J88-H88 -> -405997.83 | H88: 4040925.9 | I88: Comparar con el cuadro de la UTE copiar la columna O | J88: =SUM(I49:I63) -> 3634928.1
G89: =J89-H89 -> 2.8318589e+08 | H89: 4.6099501e+08 | J89: =SUM(J49:J63) -> 7.441809e+08 | K89: =J89+J88 -> 7.4781582e+08
G90: =J90-H90 -> 84510.555 | H90: 470301.26 | J90: =SUM(I73:I81) -> 554811.81
G91: =J91-H91 -> 59934251 | H91: 53652688 | J91: =SUM(J73:J81) -> 1.1358694e+08 | K91: =J91+J90 -> 1.1414175e+08
G92: =J92-H92 -> -7521.1193 | H92: 21364.65 | J92: =SUM(I65:I71) -> 13843.531
G93: =J93-H93 -> 2555975.1 | H93: 1218655.9 | J93: =SUM(J65:J71) -> 3774631 | K93: =J93+J92 -> 3788474.5
G94: =J94-H94 -> 8.6573883e+08 | H94: 7219.09 | J94: =SUM(J88:J93) -> 8.6574605e+08
H95: 1096838.8
H96: 521503004

Sheet total palermo
A1: SUMATORIA RECAUDACION - PERIODO | C1: =#REF! -> #REF! | F1: Recaudación | G1: Participación | H1: Porcentaje Ofertado | I1: Porcentaje con Reducción
A2: FACTURACION HIPICAS - CAPITAL FEDERAL - HIPÓDROMO DE PALERMO | E2: Palermo | F2: =SUMIF(palermo!A:A,'total palermo'!E2,palermo!D:D) -> 403901027 | G2: =F2/F3 -> 1 | H2: =2.42%/1.21 -> 0.02 | I2: =IF(F7 > 0,H2-(H2*$E$23),H2) -> 0.02 | L2: 5640321
A3: TOTALES | F3: =SUM(F2:F2) -> 403901027 | G3: =F3/F3 -> 1 | K3: =2.42*0.84 -> 2.0328 | L3: 6505234
L4: 5476622
A5: RECAUDACIÓN PALERMO | F5: =+F3 -> 403901027 | L5: =SUM(L2:L4) -> 17622177
A6: TOPE ESTIPULADO | F6: =75000000 -> 75000000 | L6: =L5*K3/100 -> 358223.61
A7: EXCEDENTE - PORCENTAJE SOBRE TOPE | E7: =IF(F7>0,IF(F7/F6>E9,0.25,F7/F6),I2) -> 0.25 | F7: =+F3-F6 -> 328901027
A8: LÍMITE DE REDUCCIÓN DE PORCENTAJE
B9: Hípicas | D9: 3.1.4 | E9: 0.25
A11: FACTURACIÓN | F11: Recaudación | J11: Facturación UTE
F12: Dentro del tope | G12: Sobre el tope | H12: Total | I12: Control | J12: Importe sobre Recaudación dentro del Tope | K12: Descuento 16% sobre Recaudación dentro del Tope | L12: Importe sobre Recaduación Sobre el Tope | M12: Descuento 16% sobre Recaduación Sobre el Tope | N12: Monto a Facturar | O12: Descuento 16% | P12: I.V.A. | Q12: Total
A13: FACTURACION HIPICAS - CAPITAL FEDERAL
B14: Hípicas - Hipódromo de Palermo | F14: =IF(F7>0,$F$7*$G$2,F2) -> 328901027 | G14: =F6 -> 75000000 | H14: =SUM(F14:G14) -> 403901027 | I14: =IF(F3=H14,"OK","ERROR") -> OK | J14: =F14*$H$2 -> 6578020.5 | K14: =-J14*0.16 -> -1052483.3 | L14: =G14*$I$18 -> 0 | M14: =-L14*0.16 -> 0 | N14: =+J14+L14 -> 6578020.5 | O14: =K14+M14 -> -1052483.3 | P14: =(N14+O14)*0.21 -> 1160362.8 | Q14: =N14+O14+P14 -> 6685900.1
A15: FACTURACIÓN RECAUDACION EXCEDENTE AL TOPE | F15: =SUM(F13:F14) -> 328901027 | G15: =SUM(G13:G14) -> 75000000 | H15: =SUM(H13:H14) -> 403901027 | J15: =SUM(J14:J14) -> 6578020.5 | K15: =SUM(K14:K14) -> -1052483.3 | L15: =SUM(L14:L14) -> 0 | M15: =SUM(M14:M14) -> 0 | N15: =SUM(N14:N14) -> 6578020.5 | O15: =SUM(O14:O14) -> -1052483.3 | P15: =SUM(P14:P14) -> 1160362.8 | Q15: =SUM(Q14:Q14) -> 6685900.1

Sheet total La plata y san isidro
A1: SUMATORIA RECAUDACION - PERIODO | C1: 01-12 al 07-12-2018 | E1: Recaudación | F1: Participación | G1: Porcentaje Ofertado | H1: Porcentaje con Reducción
A2: FACTURACION HIPICAS - CAPITAL FEDERAL | D2: San Isidro | E2: =SUMIF('la plata y san isidro'!A:A,'total La plata y san isidro'!D2,'la plata y san isidro'!D:D) -> 518690515 | F2: =$E$2/E5 -> 0.39946476 | G2: =2.42%/1.21 -> 0.02 | H2: =IF(F10 > 0,G2-(G2*$E$10),G2) -> 0.015
A3: FACTURACION HIPICAS - CAPITAL FEDERAL | D3: La Plata | E3: =SUMIF('la plata y san isidro'!A:A,'total La plata y san isidro'!D3,'la plata y san isidro'!D:D) -> 375872214 | F3: =$E$3/E5 -> 0.28947455 | G3: =2.42%/1.21 -> 0.02 | H3: =IF(F10 > 0,G3-(G3*$E$10),G3) -> 0.015
A4: FACTURACION HIPICAS - CAPITAL FEDERAL | D4: Palermo | E4: =+'total palermo'!F2 -> 403901027 | F4: =$E$4/E5 -> 0.31106069 | G4: =2.42%/1.21 -> 0.02 | H4: =IF(F10 > 0,G4-(G4*$E$10),G4) -> 0.015
A5: TOTALES | E5: =SUM(E2:E4) -> 1298463756 | F5: =E5/E5 -> 1
A7: RECAUDACIÓN PALERMO
A8: RECAUDACIÓN SAN ISIDRO Y LA PLATA + PALERMO | F8: =E5 -> 1298463756
A9: TOPE ESTIPULADO | F9: 75000000
A10: EXCEDENTE - PORCENTAJE SOBRE TOPE | E10: =IF(F10>0,IF(F10/F9>E12,0.25,F10/F9),H2) -> 0.25 | F10: =+E5-F9 -> 1223463756
A11: LÍMITE DE REDUCCIÓN DE PORCENTAJE
B12: Hípicas | D12: 3.1.4 | E12: 0.25
A14: FACTURACIÓN | E14: Recaudación | I14: Facturación UTE
E15: Dentro del tope | F15: Sobre el tope | G15: Total | H15: Control | I15: Importe sobre Recaudación dentro del Tope | J15: Descuento 16% sobre Recaudación dentro del Tope | K15: Importe sobre Recaduación Sobre el Tope | L15: Descuento 16% sobre Recaduación Sobre el Tope | M15: Monto a Facturar | N15: Descuento 16% | O15: saldo | P15: 0.05 | Q15: I.V.A. | R15: Total
A16: FACTURACION HIPICAS - CAPITAL FEDERAL
D17: Palermo | E17: =IF($F$10>0,($F$8-$F$10)*$F4,E4) -> 23329551 | F17: =IF(F10>0,$F$10*$F$4,0) -> 3.8057148e+08 | G17: =SUM(E17:F17) -> 403901027 | I17: =E17*$G$2 -> 466591.03 | J17: =-I17*0.16 -> -74654.565 | K17: =F17*$H$4 -> 5708572.1 | L17: =-K17*0.16 -> -913371.54 | M17: =+I17+K17 -> 6175163.2 | N17: =J17+L17 -> -988026.11 | O17: =+M17+N17 -> 5187137.1 | P17: =-O17*0.05 -> -259356.85 | Q17: =(M17+N17+P17)*0.21 -> 1034833.8 | R17: =M17+N17+Q17+P17 -> 5962614
B18: Hípicas | D18: San Isidro | E18: =IF($F$10>0,($F$8-$F$10)*$F2,E2) -> 29959857 | F18: =IF(F10>0,$F$10*$F$2,0) -> 4.8873066e+08 | G18: =SUM(E18:F18) -> 5.1869052e+08 | H18: =IF(E2=G18,"OK","ERROR") -> OK | I18: =E18*$G$2 -> 599197.14 | J18: =-I18*0.16 -> -95871.543 | K18: =F18*$H$3 -> 7330959.9 | L18: =-K18*0.16 -> -1172953.6 | M18: =+I18+K18 -> 7930157 | N18: =J18+L18 -> -1268825.1 | O18: =+M18+N18 -> 6661331.9 | P18: =-O18*0.05 -> -333066.59 | Q18: =(M18+N18+P18)*0.21 -> 1328935.7 | R18: =M18+N18+Q18+P18 -> 7657201
D19: La Plata | E19: =IF($F$10>0,($F$8-$F$10)*$F3,E3) -> 21710591 | F19: =IF(F10>0,$F$10*$F$3,0) -> 3.5416162e+08 | G19: =SUM(E19:F19) -> 375872214 | H19: =IF(E3=G19,"OK","ERROR") -> OK | I19: =E19*$G$3 -> 434211.83 | J19: =-I19*0.16 -> -69473.892 | K19: =F19*$H$3 -> 5312424.3 | L19: =-K19*0.16 -> -849987.89 | M19: =+I19+K19 -> 5746636.2 | N19: =J19+L19 -> -919461.79 | O19: =+M19+N19 -> 4827174.4 | P19: =-O19*0.05 -> -241358.72 | Q19: =(M19+N19+P19)*0.21 -> 963021.29 | R19: =M19+N19+Q19+P19 -> 5548837
A20: FACTURACIÓN RECAUDACION EXCEDENTE AL TOPE | E20: =SUM(E17:E19) -> 75000000 | F20: =SUM(F17:F19) -> 1223463756 | G20: =SUM(G17:G19) -> 1298463756 | I20: =SUM(I17:I19) -> 1500000 | J20: =SUM(J18:J19) -> -165345.44 | K20: =SUM(K17:K19) -> 18351956 | L20: =SUM(L17:L19) -> -2936313 | M20: =SUM(M17:M19) -> 19851956 | N20: =SUM(N17:N19) -> -3176313 | Q20: =SUM(Q17:Q19) -> 3326790.8 | R20: =SUM(R17:R19) -> 19168652
V22: comparar con la UTE
N23: PALERMO COM. | O23: =+I17+J17 -> 391936.46 | P23: =-O23*0.05 -> -19596.823 | Q23: =(O23+P23)*0.21 -> 78191.325 | R23: =+O23+P23+Q23 -> 450530.97 | V23: 493416.92 | W23: =R23-V23 -> -42885.954
N24: PALERMO REDUCIDO | O24: =+K17+L17 -> 4795200.6 | P24: =-O24*0.05 -> -239760.03 | Q24: =(O24+P24)*0.21 -> 956642.52 | R24: =+O24+P24+Q24 -> 5512083.1 | S24: =R24+R23 -> 5962614 | V24: 6284936.7 | W24: =R24-V24 -> -772853.66
N25: S.ISIDRO COMPLETO | O25: =+I18+J18 -> 503325.6 | P25: =-O25*0.05 -> -25166.28 | Q25: =(O25+P25)*0.21 -> 100413.46 | R25: =+O25+P25+Q25 -> 578572.78 | V25: 582537.59 | W25: =R25-V25 -> -3964.8095
N26: S.ISIDRO REDUCIDO | O26: =+K18+L18 -> 6158006.3 | P26: =-O26*0.05 -> -307900.31 | Q26: =(O26+P26)*0.21 -> 1228522.3 | R26: =+O26+P26+Q26 -> 7078628.2 | S26: =R26+R25 -> 7657201 | V26: 7420118.2 | W26: =R26-V26 -> -341489.99
N27: L.PLATA COMP | O27: =+I19+J19 -> 364737.94 | P27: =-O27*0.05 -> -18236.897 | Q27: =(O27+P27)*0.21 -> 72765.218 | R27: =+O27+P27+Q27 -> 419266.26 | V27: 372415.49 | W27: =R27-V27 -> 46850.764
N28: L.PLATA REDUC | O28: =+K19+L19 -> 4462436.4 | P28: =-O28*0.05 -> -223121.82 | Q28: =(O28+P28)*0.21 -> 890256.07 | R28: =+O28+P28+Q28 -> 5129570.7 | S28: =R28+R27 -> 5548837 | T28: =S28+S26 -> 13206038 | V28: 4743671.6 | W28: =R28-V28 -> 385899.13
R29: =SUM(R23:R28) -> 19168652
